Workbook

Sheet Revisions
A1: 1 | B1: Scoring Guide | C1: Review/revise all questions .2 and .3 Scoring guidance - EXCEPT 3.2-3.3 as these have already been revised. This may result in updating the Question field.
A2: 2 | B2: Scoring Guide | C2: Review/revise all questions .2 and .3 Typical Evidence and Evaluation Boundaries - EXCEPT 3.2-3.3 as these have already been revised.
A3: 3 | B3: Scoring Guide | C3: Review/revise all questions .2 and .3 as necessary.
A4: 4 | B4: Review Entry | C4: Re-introduce the .2 and .3 questions.

Sheet Rev Log
A1: No. | B1: Date | C1: Revision
A2: 1 | B2: 46248 | C2: Initial release.

Sheet Overview
A1: Worksheet | B1: Purpose
A2: Instructions | B2: Provides the basic rules for using the QSR workbook, including how to complete the Review Register and Review Entry fields and how scoring, evidence, root cause, and follow-up should be handled.
A3: Review Register | B3: Serves as the master list of review instances and records review-level information such as project, reviewer, review type, status, dates, and review time.
A4: Review Entry | B4: Captures the question-by-question results for each review, including evidence, PM clarification, observations, root cause, quality-system relationship, and follow-up needs.
A5: Scoring Guide | B5: Provides concise 3/2/1 scoring criteria, typical evidence, and question boundaries to help reviewers apply ratings consistently.
A6: Source Matrix | B6: Maps each QSR question to the controlling source documents, sections, pages, and requirements that support the expectation being reviewed.
A7: Actions | B7: Tracks corrective actions, improvement opportunities, ownership, due dates, status, and closure evidence resulting from QSR findings.
A8: KPI Summary | B8: Summarizes QSR performance, review-area results, root-cause trends, evidence-control metrics, completion, and review-effort measures.
A9: Lists | B9: Stores the controlled dropdown values used throughout the workbook, such as review types, statuses, evidence categories, root causes, and action classifications.

Sheet Instructions
A1: Review Register Worksheet
A2: Review Register Column | B2: Purpose
A3: Review ID | B3: Unique identifier for the review instance. Use the established format, such as Project ID 01-R01.
A4: Project ID | B4: Project/job number for the project being reviewed. Project selection criteria: - PM diversity where practical - active projects far enough along to provide meaningful evidence - completed projects preferably within the last 6–12 months - mix of small, medium, and larger projects - mix of routine and 1–2 known-challenged projects per BU - exclusions for projects that are too new, too small, administrative-only, or unusually atypical
A5: Project Description | B5: Short project name or description sufficient to identify the project.
A6: Project Manager | B6: PM responsible for the project being reviewed.
A7: Business Unit | B7: Business Unit that owns or executes the project.
A8: Project Status | B8: Select the project lifecycle status used for the review, currently Active or Completed.
A9: Sold Labor Revenue | B9: Provides a simple measure of project labor size to support comparison of QSR results across projects of different scale. - Labor revenue included in the approved project estimate at the time the project was sold. - Enter the original sold labor revenue from the approved estimate/proposal baseline. Do not update for later changes unless the original commercial baseline itself was formally revised.
A10: Sold Labor Margin % | B10: Establishes the original labor profitability expectation at the time the project was sold for comparison to subsequent performance. - Labor gross margin percentage reflected in the approved estimate at the time the project was sold. - Enter the labor margin percentage from the original approved estimate/proposal baseline. Use the same underlying source as Sold Labor Revenue.
A11: Labor Margin at Review % | B11: Captures the project’s labor margin performance at the time of the review to provide financial-performance context for the QSR results. - The project’s current forecast labor margin at the time of the QSR, or final actual labor margin if the project is complete. - For an active project, use the current forecast/EAC labor margin available at the time of review. For a completed project, use the final actual labor margin.
A12: Labor Margin Variance | B12: Shows the degree of labor margin improvement or erosion relative to the sold labor margin, enabling comparison of financial performance across reviewed projects. - Difference between the project’s labor margin at review and its sold labor margin. - Calculate as: Labor Margin at Review % – Sold Labor Margin %. A negative result indicates margin erosion; a positive result indicates improvement.
A13: Review Sequence | B13: Numeric sequence of reviews for the same project. Use 1 for the initial review, 2 for the first follow-up, etc.
... A20: Notes | B20: Optional review-level context that is useful but does not belong in the individual question results.
A22: Review Entry Worksheet
A23: Review Entry Column | B23: Purpose
A24: Review ID | B24: Identifies the review instance. This links the question result back to the corresponding review in the Review Register.
A25: Review Area | B25: The QSR review area associated with the question, such as Risk Management or Change Management. This is predefined and should not be edited.
A26: Question ID | B26: Unique identifier for the controlled QSR question, such as 4.2. This is predefined and should not be edited.
A27: Controlled Question Text | B27: The approved QSR question being evaluated. This is predefined and should not be edited.
A28: Primary Intent | B28: Brief explanation of what the question is intended to evaluate. Use this to help interpret the question consistently.
A29: Result | B29: Select 3 - Meets Expectation, 2 - Partially Meets Expectation, 1 - Does Not Meet Expectation, N/A - Not Applicable or UTD - Unable To Determine based on the Scoring Guide.
A30: Evidence Status | B30: Select the status that best describes the evidence supporting the result, such as Expected Evidence Found, Acceptable Alternate Evidence, Incomplete Evidence, or Missing Evidence.
A31: Evidence Reviewed / Location | B31: Identify the specific evidence actually reviewed and where it was found or linked so another reviewer could retrace the basis for the rating.
A32: PM Clarification Used? | B32: Select Yes if PM clarification materially helped determine applicability, locate evidence, reconcile records, or understand how the control was performed. Otherwise select No.
A33: PM Clarification Summary | B33: If clarification was used, briefly summarize the information that affected the review conclusion. PM explanation provides context but does not replace required evidence.
A34: Reviewer Observation | B34: For a result of 1 or 2, briefly describe what did not meet the expectation and the material gap observed. For a result of 3, an observation is optional unless useful context should be retained.
... A37: Follow-Up Required? | B37: Select Yes when a Follow-Up Review is needed to verify that the underlying control or expectation has been satisfactorily addressed. A Follow-Up Review is not required solely because an action was created or completed. Follow-Up Reviews are targeted to the specific gap(s) or control(s) requiring verification rather than repeating the full project review.
A39: Scoring Guide Worksheet
A40: Use the Scoring Guide worksheet to help reviewers assign consistent ratings for each QSR question. The Scoring Guide is intended to improve consistency between reviewers. It does not replace reviewer judgment, the controlling source requirements, or the need to consider the project’s lifecycle stage and applicability. N/A and UTD are handled under the separate QSR scoring rules rather than the 3/2/1 question-specific criteria.
A41: The reviewer should filter to the applicable Review Area or Question ID, compare the available evidence to the 3/2/1 criteria, consider the Typical Evidence and Key Boundary, and then enter the selected result on the Review Entry worksheet.
A42: For each question, the worksheet provides:
A43: Scoring Guide Column | B43: Purpose
A44: Review Area | B44: Identifies the QSR review area the question belongs to.
A45: Question ID | B45: Identifies the specific controlled question.
A46: Controlled Question | B46: Shows the approved question being evaluated.
A47: 3 — Meets Expectation | B47: Describes what satisfactory performance looks like when the expectation is substantially fulfilled and supported by evidence.
A48: 2 — Partially Meets Expectation | B48: Describes conditions where meaningful elements are present, but execution, evidence, maintenance, timeliness, approval, or effectiveness is materially incomplete.
A49: 1 — Does Not Meet Expectation | B49: Describes conditions where the applicable expectation is not met, is ineffective, or cannot be reliably verified.
A50: Typical Evidence | B50: Gives examples of records that may support the reviewer’s conclusion. These are examples, not an exhaustive checklist.
A51: Evaluation Boundary | B51: Clarifies what the question is intended to score and helps prevent the same issue from being counted under multiple questions unless a separate control also failed.
A53: Source Matrix Worksheet
A54: Use the Source Matrix worksheet to identify the controlling source requirements that support each QSR question and to help the reviewer verify the basis for the scoring expectation.
A55: The reviewer should filter the worksheet by Review Area and/or Question ID when additional source context is needed. Multiple rows for a question indicate that the expectation is supported by more than one applicable source.
A56: The Source Matrix is intended to make the QSR requirements traceable and verifiable. It should be used together with the Scoring Guide: the Scoring Guide explains how to evaluate the question, while the Source Matrix identifies the controlling documents behind that expectation.
A57: Source Matrix Column | B57: Purpose
A58: Review Area | B58: Identifies the QSR review area associated with the source reference.
A59: Question ID | B59: Identifies the specific QSR question supported by the source. A question may have multiple source-reference rows.
A60: Source Document | B60: Identifies the policy, SOP, standard, Project Workbook, Project Notebook, or other controlling QSR source containing the applicable requirement or guidance.
A61: Section | B61: Identifies the specific section, subsection, worksheet, agenda, or other location within the source.
A62: Page | B62: Provides the applicable page number or page range where available. N/A is used where conventional page numbering does not apply, such as a workbook worksheet.
A63: Requirement / Relevance | B63: Briefly explains what the cited source establishes and why it is relevant to the associated QSR question.
A64: Source File | B64: Identifies the specific source file used for the reference.
A66: Actions Worksheet
A67: An Action record is required for every Review Entry result of 1 — Does Not Meet Expectation or 2 — Partially Meets Expectation. Multiple related gaps may be addressed through a single Action when appropriate, provided each gap remains clearly traceable to that Action.
A68: Actions Column | B68: Purpose
A69: Action ID | B69: Unique identifier for the action or improvement item so it can be tracked through closure.
A70: Review ID | B70: Review that generated the action. Use the corresponding Review ID from the Review Register.
A71: Question ID | B71: QSR question associated with the finding or improvement opportunity.
A72: Action Type | B72: Select the category that best describes the type of action or improvement being addressed: - Project Correction - The issue is specific to the reviewed project and should be corrected within that project. It does not necessarily indicate a problem with the quality system itself. - Standard / Process - The finding indicates that an SOP, standard, process requirement, or workflow may need clarification, revision, or improvement. - Tool / Template - The action involves changing or improving a standard tool, workbook, template, form, checklist, or other execution aid. - Training / Communication - The response should primarily address understanding or awareness through training, coaching, guidance, or communication. - Governance - The issue requires improved oversight, accountability, enforcement, management review, or another governance mechanism rather than simply changing the written standard. - Further Evaluation - There is enough evidence to warrant follow-up, but it is not yet clear what type of improvement is appropriate. Additional analysis is needed before deciding the action.
A73: Action / Improvement | B73: Briefly describe the specific corrective action, improvement, verification, or follow-up that is required. Make it clear enough to determine when it has been completed.
A74: Owner | B74: Required for every Action. Identify the person accountable for completing or coordinating the action. Project-specific corrective actions are normally owned by the Project Manager; system-level actions should be assigned to the appropriate functional or quality-system owner.
A75: Due Date | B75: Required for every Action. Enter the agreed target date for completing the action.
A76: Status | B76: Required for every Action. Select the current status of the action using the available dropdown values and keep it current through closure.
A77: Closure Evidence | B77: Required before an Action is closed. Identify the evidence or closure note demonstrating what was completed and that the issue was addressed. Include the applicable record or location where appropriate.
A78: Closed Date | B78: Date the action was verified as complete and closed.
A79: Notes | B79: Optional additional context that is useful for managing or understanding the action but does not belong in the other fields.
A81: List Worksheet
A82: List - Primary Root Cause | B82: Definition
A83: Standard Unclear | B83: The applicable standard exists, but its requirements, instructions, or expected outcomes are ambiguous, incomplete, conflicting, or insufficiently specific to support consistent execution. Correcting the standard should reduce recurrence.
A84: Tool / Template Friction | B84: The prescribed tool, template, or workflow materially makes proper execution difficult, inefficient, duplicative, or prone to error. Correcting the enabling mechanism should make compliance easier and more reliable.
A85: Training Gap | B85: The standard exists and is sufficiently clear, but the associate was not adequately trained or prepared to execute it correctly. Correcting the knowledge or skill gap should reduce recurrence.
A86: Governance / Enforcement Gap | B86: Management expectations, oversight, accountability, reinforcement, escalation, or follow-through were insufficient to drive consistent execution of the standard. This identifies a management-system problem rather than an isolated individual failure.
A87: Individual Adherence Gap | B87: The standard was sufficiently clear, appropriate training and tools were available, reasonable capacity existed, and management expectations were established, but the associate nevertheless did not perform the required activity. This is the residual category for an individual execution/accountability failure after other systemic causes have been reasonably ruled out.
B88: Guidance
B89: Was the standard itself sufficiently clear? - No → Standard Unclear Did the tool/template/workflow enable reasonable execution? - No → Tool / Template Friction Was the person adequately trained to perform it? - No → Training Gap Were expectations, accountability, and management reinforcement adequate? - No → Governance / Enforcement Gap If all of the above were adequate, did the person still fail to execute? - Yes → Individual Adherence Gap

Sheet Review Register
A1: Review ID | B1: Project ID | C1: Project Description | D1: Project Manager | E1: Business Unit | F1: Project Status | G1: Sold Labor Revenue | H1: Sold Labor Margin % | I1: Labor Margin at Review % | J1: Labor Margin Variance | K1: Review Sequence | L1: Review Type | M1: Reviewer | N1: Review Status | O1: Review Start Date | P1: Review Completion Date | Q1: Review Time (Hours) | R1: Notes
A2: Project ID 01-R01 | B2: Project ID 01 | J2: =IF(OR(H2="",I2=""),"",I2-H2) | K2: 1 | L2: Initial Review | N2: Not Started
A3: Project ID 02-R01 | B3: Project ID 02 | J3: =IF(OR(H3="",I3=""),"",I3-H3) | K3: 1 | L3: Initial Review | N3: Not Started
A4: Project ID 03-R01 | B4: Project ID 03 | J4: =IF(OR(H4="",I4=""),"",I4-H4) | K4: 1 | L4: Initial Review | N4: Not Started
A5: Project ID 04-R01 | B5: Project ID 04 | J5: =IF(OR(H5="",I5=""),"",I5-H5) | K5: 1 | L5: Initial Review | N5: Not Started
A6: Project ID 05-R01 | B6: Project ID 05 | J6: =IF(OR(H6="",I6=""),"",I6-H6) | K6: 1 | L6: Initial Review | N6: Not Started

Sheet Review Entry-Complete
A1: Review ID | B1: Review Area | C1: Question ID | D1: Controlled Question Text | E1: Primary Intent | F1: Evaluation Boundary | G1: Result | H1: Evidence Status | I1: Evidence Reviewed / Location | J1: PM Clarification Used? | K1: PM Clarification Summary | L1: Reviewer Observation | M1: Primary Root Cause | N1: Root-Cause Explanation | O1: Quality-System-Related? | P1: Follow-Up Required? | Q1: Reviewer | R1: Project Manager
A2: Project ID 01-R01 | B2: Project Record Accessibility / Organization | C2: 1.1 | D2: Are project records maintained in the Project Vault or another location permitted by the Project Vault SOP? | E2: Verify that material project records are stored in approved repositories with required traceability. | F2: Scores approved storage location and repository traceability; do not also score general findability or overall record quality unless a separate failure exists. | Q2: =IF('Review Register'!M2="","",'Review Register'!M2) | R2: =IF('Review Register'!D2="","",'Review Register'!D2)
A3: Project ID 01-R01 | B3: Project Record Accessibility / Organization | C3: 1.2 | D3: Are the project’s primary source records readily locatable so the reviewer can understand what was sold, how the project was established for execution, and where supporting QSR evidence is maintained? | E3: Verify that primary source records can be readily located and used to establish the project basis and supporting evidence. | F3: Scores findability and navigation; do not score the substantive quality of each underlying process record here. | Q3: =IF('Review Register'!M2="","",'Review Register'!M2) | R3: =IF('Review Register'!D2="","",'Review Register'!D2)
A4: Project ID 01-R01 | B4: Project Record Accessibility / Organization | C4: 1.3 | D4: Are project records organized, current, controlled, and sufficiently complete to support project execution, traceability, and reliable review? | E4: Verify the overall integrity, currency, control, and completeness of the project record for the lifecycle stage. | F4: Scores overall record integrity; do not duplicate isolated process-artifact failures unless they materially impair the overall project record. | Q4: =IF('Review Register'!M2="","",'Review Register'!M2) | R4: =IF('Review Register'!D2="","",'Review Register'!D2)
A5: Project ID 01-R01 | B5: Sales Handoff / Kickoff | C5: 2.1 | D5: Was Sales Handoff documented and effective in transferring the commercial, scope, schedule, budget, risk, client, and project-background information required by the PM and project team? | E5: Verify effective transfer of the information needed to move the project from sales/estimating into execution. | F5: Scores Sales Handoff; do not duplicate Internal Kickoff, Client Kickoff, or later project-planning controls unless separately deficient. | Q5: =IF('Review Register'!M2="","",'Review Register'!M2) | R5: =IF('Review Register'!D2="","",'Review Register'!D2)
A6: Project ID 01-R01 | B6: Sales Handoff / Kickoff | C6: 2.2 | D6: Was the Internal Kickoff documented and effective in aligning the project team on scope, schedule, budget, responsibilities, quality expectations, risks, and the execution approach? | E6: Verify internal project-team alignment before or at the start of execution. | F6: Scores Internal Kickoff alignment; do not duplicate the Sales Handoff transfer or Client Kickoff alignment unless separately deficient. | Q6: =IF('Review Register'!M2="","",'Review Register'!M2) | R6: =IF('Review Register'!D2="","",'Review Register'!D2)
A7: Project ID 01-R01 | B7: Sales Handoff / Kickoff | C7: 2.3 | D7: Was the Client Kickoff documented and effective in aligning ETG and the client on scope, deliverables, schedule, responsibilities, communications, quality, risks, dependencies, approvals, and success expectations? | E7: Verify alignment between ETG and the client on how the project will be executed and governed. | F7: Scores Client Kickoff alignment; do not duplicate Internal Kickoff or ongoing client communications and project reviews unless separately deficient. | Q7: =IF('Review Register'!M2="","",'Review Register'!M2) | R7: =IF('Review Register'!D2="","",'Review Register'!D2)
A8: Project ID 01-R01 | B8: Project Planning / Workbook Usage | C8: 3.1 | D8: Were all applicable PMLC project-management planning areas considered and appropriately tailored to the project’s size, complexity, risk, contract, and execution needs? | E8: Verify that project-management planning was completed and appropriately tailored to the project. | F8: Scores adequacy and tailoring of planning; do not duplicate Workbook maintenance or specific roles/communications controls unless separately deficient. | Q8: =IF('Review Register'!M2="","",'Review Register'!M2) | R8: =IF('Review Register'!D2="","",'Review Register'!D2)
A9: Project ID 01-R01 | B9: Project Planning / Workbook Usage | C9: 3.2 | D9: Were applicable Project Workbook components populated with sufficient, current, and usable information to support project execution, monitoring, and control? | E9: Verify that applicable Project Workbook components are populated and maintained as usable project-management records. | F9: Scores Workbook content and usability; do not duplicate the broader planning approach or specific risk/change controls unless separately deficient. | Q9: =IF('Review Register'!M2="","",'Review Register'!M2) | R9: =IF('Review Register'!D2="","",'Review Register'!D2)
A10: Project ID 01-R01 | B10: Project Planning / Workbook Usage | C10: 3.3 | D10: Were project roles, responsibilities, deliverables, stakeholder needs, communications, resources, and schedule commitments clearly established and maintained? | E10: Verify that the people, deliverables, communications, resources, and schedule commitments needed for execution are clearly established and maintained. | F10: Scores these execution-planning elements; do not duplicate general Workbook completeness or later review-cadence controls unless separately deficient. | Q10: =IF('Review Register'!M2="","",'Review Register'!M2) | R10: =IF('Review Register'!D2="","",'Review Register'!D2)
A11: Project ID 01-R01 | B11: Risk Management | C11: 4.1 | D11: Were material project risks identified, assessed, and documented at appropriate points beginning with estimating and Sales Handoff? | E11: Verify timely identification, assessment, and documentation of material project risks beginning before execution. | F11: Scores risk identification and assessment; do not duplicate Risk Registry usage or ongoing risk review/mitigation unless separately deficient. | Q11: =IF('Review Register'!M2="","",'Review Register'!M2) | R11: =IF('Review Register'!D2="","",'Review Register'!D2)
A12: Project ID 01-R01 | B12: Risk Management | C12: 4.2 | D12: Was the Project Workbook Risk Registry used and maintained, or was an acceptable equivalent clearly identified and traceable through the Project Workbook or project records? | E12: Verify use of the standard Risk Registry or a clearly identified, traceable acceptable equivalent. | F12: Scores the risk-recording mechanism and traceability; do not duplicate the quality of initial risk identification or ongoing risk management unless separately deficient. | Q12: =IF('Review Register'!M2="","",'Review Register'!M2) | R12: =IF('Review Register'!D2="","",'Review Register'!D2)
A13: Project ID 01-R01 | B13: Risk Management | C13: 4.3 | D13: Were risks reviewed throughout execution, with risk status, impacts, mitigation actions, owners, changes, and dispositions updated as warranted? | E13: Verify active management of identified risks throughout project execution. | F13: Scores ongoing risk review, mitigation, ownership, and disposition; do not duplicate initial risk identification or registry existence unless separately deficient. | Q13: =IF('Review Register'!M2="","",'Review Register'!M2) | R13: =IF('Review Register'!D2="","",'Review Register'!D2)
A14: Project ID 01-R01 | B14: Change Management | C14: 5.1 | D14: Were potential or actual changes to scope, schedule, budget, requirements, design, or other approved project baselines identified and documented when they arose? | E14: Verify that changes to approved project baselines are recognized and documented when they arise. | F14: Scores change identification and documentation; do not duplicate authorization/approval or incorporation of approved changes unless separately deficient. | Q14: =IF('Review Register'!M2="","",'Review Register'!M2) | R14: =IF('Review Register'!D2="","",'Review Register'!D2)
A15: Project ID 01-R01 | B15: Change Management | C15: 5.2 | D15: Were changes evaluated, communicated, authorized, and approved before out-of-scope or at-risk work proceeded, except where the contract expressly permitted another approach? | E15: Verify that changes are evaluated and appropriately authorized before affected work proceeds. | F15: Scores evaluation, communication, authorization, and approval; do not duplicate initial change identification or downstream record updates unless separately deficient. | Q15: =IF('Review Register'!M2="","",'Review Register'!M2) | R15: =IF('Review Register'!D2="","",'Review Register'!D2)
A16: Project ID 01-R01 | B16: Change Management | C16: 5.3 | D16: Were approved changes fully incorporated into applicable project-management, financial, schedule, technical, contractual, and client records? | E16: Verify that approved changes are fully incorporated into the records and baselines they affect. | F16: Scores implementation of approved changes into records; do not duplicate whether the change was identified or approved unless separately deficient. | Q16: =IF('Review Register'!M2="","",'Review Register'!M2) | R16: =IF('Review Register'!D2="","",'Review Register'!D2)
A17: Project ID 01-R01 | B17: Project Monitoring / Review Cadence | C17: 6.1 | D17: Were project reviews conducted at required or appropriate intervals, including applicable project checkpoints and recurring project reviews? | E17: Verify that project reviews and checkpoints occur at required or appropriate intervals. | F17: Scores review occurrence and cadence; do not duplicate the content of reviews or follow-through on resulting actions unless separately deficient. | Q17: =IF('Review Register'!M2="","",'Review Register'!M2) | R17: =IF('Review Register'!D2="","",'Review Register'!D2)
A18: Project ID 01-R01 | B18: Project Monitoring / Review Cadence | C18: 6.2 | D18: Did project reviews address current scope, schedule, budget and forecast, risks, changes, deliverables, quality, resources, client needs, and other material project conditions as applicable? | E18: Verify that project reviews address the material conditions needed to understand and control project performance. | F18: Scores review content and coverage; do not duplicate review cadence or action follow-through unless separately deficient. | Q18: =IF('Review Register'!M2="","",'Review Register'!M2) | R18: =IF('Review Register'!D2="","",'Review Register'!D2)
A19: Project ID 01-R01 | B19: Project Monitoring / Review Cadence | C19: 6.3 | D19: Were decisions, actions, owners, due dates, escalations, and follow-up resulting from project reviews documented and carried through? | E19: Verify that project-review decisions and actions are documented, assigned, escalated where needed, and followed through. | F19: Scores action management resulting from reviews; do not duplicate whether reviews occurred or what topics they covered unless separately deficient. | Q19: =IF('Review Register'!M2="","",'Review Register'!M2) | R19: =IF('Review Register'!D2="","",'Review Register'!D2)
A20: Project ID 01-R01 | B20: Closeout / Lessons Learned | C20: 7.1 | D20: Were applicable technical, administrative, financial, contractual, and client closeout activities completed and documented? | E20: Verify completion and documentation of the applicable overall project closeout activities. | F20: Scores overall closeout completion; do not duplicate specific deliverable/acceptance records or lessons learned unless separately deficient. | Q20: =IF('Review Register'!M2="","",'Review Register'!M2) | R20: =IF('Review Register'!D2="","",'Review Register'!D2)
A21: Project ID 01-R01 | B21: Closeout / Lessons Learned | C21: 7.2 | D21: Were final deliverables, testing and acceptance records, turnover information, approved technical records, client signoffs, and other required closeout records completed and stored appropriately? | E21: Verify completion, approval, turnover, and proper storage of required final project records and deliverables. | F21: Scores final deliverable and acceptance records; do not duplicate broader administrative/financial closeout or lessons learned unless separately deficient. | Q21: =IF('Review Register'!M2="","",'Review Register'!M2) | R21: =IF('Review Register'!D2="","",'Review Register'!D2)
A22: Project ID 01-R01 | B22: Closeout / Lessons Learned | C22: 7.3 | D22: Were lessons learned captured during the project and consolidated at closeout into useful recommendations, with project-specific and quality-system improvement opportunities identified for follow-up where warranted? | E22: Verify that lessons learned are captured and converted into useful project-specific and quality-system improvement opportunities. | F22: Scores lessons learned and improvement capture; do not duplicate general closeout completion or final deliverable records unless separately deficient. | Q22: =IF('Review Register'!M2="","",'Review Register'!M2) | R22: =IF('Review Register'!D2="","",'Review Register'!D2)
A23: Project ID 02-R01 | B23: Project Record Accessibility / Organization | C23: 1.1 | D23: Are project records maintained in the Project Vault or another location permitted by the Project Vault SOP? | E23: Verify that material project records are stored in approved repositories with required traceability. | F23: Scores approved storage location and repository traceability; do not also score general findability or overall record quality unless a separate failure exists. | Q23: =IF('Review Register'!M3="","",'Review Register'!M3) | R23: =IF('Review Register'!D3="","",'Review Register'!D3)
A24: Project ID 02-R01 | B24: Project Record Accessibility / Organization | C24: 1.2 | D24: Are the project’s primary source records readily locatable so the reviewer can understand what was sold, how the project was established for execution, and where supporting QSR evidence is maintained? | E24: Verify that primary source records can be readily located and used to establish the project basis and supporting evidence. | F24: Scores findability and navigation; do not score the substantive quality of each underlying process record here. | Q24: =IF('Review Register'!M3="","",'Review Register'!M3) | R24: =IF('Review Register'!D3="","",'Review Register'!D3)
A25: Project ID 02-R01 | B25: Project Record Accessibility / Organization | C25: 1.3 | D25: Are project records organized, current, controlled, and sufficiently complete to support project execution, traceability, and reliable review? | E25: Verify the overall integrity, currency, control, and completeness of the project record for the lifecycle stage. | F25: Scores overall record integrity; do not duplicate isolated process-artifact failures unless they materially impair the overall project record. | Q25: =IF('Review Register'!M3="","",'Review Register'!M3) | R25: =IF('Review Register'!D3="","",'Review Register'!D3)
A26: Project ID 02-R01 | B26: Sales Handoff / Kickoff | C26: 2.1 | D26: Was Sales Handoff documented and effective in transferring the commercial, scope, schedule, budget, risk, client, and project-background information required by the PM and project team? | E26: Verify effective transfer of the information needed to move the project from sales/estimating into execution. | F26: Scores Sales Handoff; do not duplicate Internal Kickoff, Client Kickoff, or later project-planning controls unless separately deficient. | Q26: =IF('Review Register'!M3="","",'Review Register'!M3) | R26: =IF('Review Register'!D3="","",'Review Register'!D3)
A27: Project ID 02-R01 | B27: Sales Handoff / Kickoff | C27: 2.2 | D27: Was the Internal Kickoff documented and effective in aligning the project team on scope, schedule, budget, responsibilities, quality expectations, risks, and the execution approach? | E27: Verify internal project-team alignment before or at the start of execution. | F27: Scores Internal Kickoff alignment; do not duplicate the Sales Handoff transfer or Client Kickoff alignment unless separately deficient. | Q27: =IF('Review Register'!M3="","",'Review Register'!M3) | R27: =IF('Review Register'!D3="","",'Review Register'!D3)
A28: Project ID 02-R01 | B28: Sales Handoff / Kickoff | C28: 2.3 | D28: Was the Client Kickoff documented and effective in aligning ETG and the client on scope, deliverables, schedule, responsibilities, communications, quality, risks, dependencies, approvals, and success expectations? | E28: Verify alignment between ETG and the client on how the project will be executed and governed. | F28: Scores Client Kickoff alignment; do not duplicate Internal Kickoff or ongoing client communications and project reviews unless separately deficient. | Q28: =IF('Review Register'!M3="","",'Review Register'!M3) | R28: =IF('Review Register'!D3="","",'Review Register'!D3)
A29: Project ID 02-R01 | B29: Project Planning / Workbook Usage | C29: 3.1 | D29: Were all applicable PMLC project-management planning areas considered and appropriately tailored to the project’s size, complexity, risk, contract, and execution needs? | E29: Verify that project-management planning was completed and appropriately tailored to the project. | F29: Scores adequacy and tailoring of planning; do not duplicate Workbook maintenance or specific roles/communications controls unless separately deficient. | Q29: =IF('Review Register'!M3="","",'Review Register'!M3) | R29: =IF('Review Register'!D3="","",'Review Register'!D3)
A30: Project ID 02-R01 | B30: Project Planning / Workbook Usage | C30: 3.2 | D30: Were applicable Project Workbook components populated with sufficient, current, and usable information to support project execution, monitoring, and control? | E30: Verify that applicable Project Workbook components are populated and maintained as usable project-management records. | F30: Scores Workbook content and usability; do not duplicate the broader planning approach or specific risk/change controls unless separately deficient. | Q30: =IF('Review Register'!M3="","",'Review Register'!M3) | R30: =IF('Review Register'!D3="","",'Review Register'!D3)
A31: Project ID 02-R01 | B31: Project Planning / Workbook Usage | C31: 3.3 | D31: Were project roles, responsibilities, deliverables, stakeholder needs, communications, resources, and schedule commitments clearly established and maintained? | E31: Verify that the people, deliverables, communications, resources, and schedule commitments needed for execution are clearly established and maintained. | F31: Scores these execution-planning elements; do not duplicate general Workbook completeness or later review-cadence controls unless separately deficient. | Q31: =IF('Review Register'!M3="","",'Review Register'!M3) | R31: =IF('Review Register'!D3="","",'Review Register'!D3)
A32: Project ID 02-R01 | B32: Risk Management | C32: 4.1 | D32: Were material project risks identified, assessed, and documented at appropriate points beginning with estimating and Sales Handoff? | E32: Verify timely identification, assessment, and documentation of material project risks beginning before execution. | F32: Scores risk identification and assessment; do not duplicate Risk Registry usage or ongoing risk review/mitigation unless separately deficient. | Q32: =IF('Review Register'!M3="","",'Review Register'!M3) | R32: =IF('Review Register'!D3="","",'Review Register'!D3)
A33: Project ID 02-R01 | B33: Risk Management | C33: 4.2 | D33: Was the Project Workbook Risk Registry used and maintained, or was an acceptable equivalent clearly identified and traceable through the Project Workbook or project records? | E33: Verify use of the standard Risk Registry or a clearly identified, traceable acceptable equivalent. | F33: Scores the risk-recording mechanism and traceability; do not duplicate the quality of initial risk identification or ongoing risk management unless separately deficient. | Q33: =IF('Review Register'!M3="","",'Review Register'!M3) | R33: =IF('Review Register'!D3="","",'Review Register'!D3)
A34: Project ID 02-R01 | B34: Risk Management | C34: 4.3 | D34: Were risks reviewed throughout execution, with risk status, impacts, mitigation actions, owners, changes, and dispositions updated as warranted? | E34: Verify active management of identified risks throughout project execution. | F34: Scores ongoing risk review, mitigation, ownership, and disposition; do not duplicate initial risk identification or registry existence unless separately deficient. | Q34: =IF('Review Register'!M3="","",'Review Register'!M3) | R34: =IF('Review Register'!D3="","",'Review Register'!D3)
A35: Project ID 02-R01 | B35: Change Management | C35: 5.1 | D35: Were potential or actual changes to scope, schedule, budget, requirements, design, or other approved project baselines identified and documented when they arose? | E35: Verify that changes to approved project baselines are recognized and documented when they arise. | F35: Scores change identification and documentation; do not duplicate authorization/approval or incorporation of approved changes unless separately deficient. | Q35: =IF('Review Register'!M3="","",'Review Register'!M3) | R35: =IF('Review Register'!D3="","",'Review Register'!D3)
A36: Project ID 02-R01 | B36: Change Management | C36: 5.2 | D36: Were changes evaluated, communicated, authorized, and approved before out-of-scope or at-risk work proceeded, except where the contract expressly permitted another approach? | E36: Verify that changes are evaluated and appropriately authorized before affected work proceeds. | F36: Scores evaluation, communication, authorization, and approval; do not duplicate initial change identification or downstream record updates unless separately deficient. | Q36: =IF('Review Register'!M3="","",'Review Register'!M3) | R36: =IF('Review Register'!D3="","",'Review Register'!D3)
A37: Project ID 02-R01 | B37: Change Management | C37: 5.3 | D37: Were approved changes fully incorporated into applicable project-management, financial, schedule, technical, contractual, and client records? | E37: Verify that approved changes are fully incorporated into the records and baselines they affect. | F37: Scores implementation of approved changes into records; do not duplicate whether the change was identified or approved unless separately deficient. | Q37: =IF('Review Register'!M3="","",'Review Register'!M3) | R37: =IF('Review Register'!D3="","",'Review Register'!D3)
A38: Project ID 02-R01 | B38: Project Monitoring / Review Cadence | C38: 6.1 | D38: Were project reviews conducted at required or appropriate intervals, including applicable project checkpoints and recurring project reviews? | E38: Verify that project reviews and checkpoints occur at required or appropriate intervals. | F38: Scores review occurrence and cadence; do not duplicate the content of reviews or follow-through on resulting actions unless separately deficient. | Q38: =IF('Review Register'!M3="","",'Review Register'!M3) | R38: =IF('Review Register'!D3="","",'Review Register'!D3)
A39: Project ID 02-R01 | B39: Project Monitoring / Review Cadence | C39: 6.2 | D39: Did project reviews address current scope, schedule, budget and forecast, risks, changes, deliverables, quality, resources, client needs, and other material project conditions as applicable? | E39: Verify that project reviews address the material conditions needed to understand and control project performance. | F39: Scores review content and coverage; do not duplicate review cadence or action follow-through unless separately deficient. | Q39: =IF('Review Register'!M3="","",'Review Register'!M3) | R39: =IF('Review Register'!D3="","",'Review Register'!D3)
A40: Project ID 02-R01 | B40: Project Monitoring / Review Cadence | C40: 6.3 | D40: Were decisions, actions, owners, due dates, escalations, and follow-up resulting from project reviews documented and carried through? | E40: Verify that project-review decisions and actions are documented, assigned, escalated where needed, and followed through. | F40: Scores action management resulting from reviews; do not duplicate whether reviews occurred or what topics they covered unless separately deficient. | Q40: =IF('Review Register'!M3="","",'Review Register'!M3) | R40: =IF('Review Register'!D3="","",'Review Register'!D3)
A41: Project ID 02-R01 | B41: Closeout / Lessons Learned | C41: 7.1 | D41: Were applicable technical, administrative, financial, contractual, and client closeout activities completed and documented? | E41: Verify completion and documentation of the applicable overall project closeout activities. | F41: Scores overall closeout completion; do not duplicate specific deliverable/acceptance records or lessons learned unless separately deficient. | Q41: =IF('Review Register'!M3="","",'Review Register'!M3) | R41: =IF('Review Register'!D3="","",'Review Register'!D3)
A42: Project ID 02-R01 | B42: Closeout / Lessons Learned | C42: 7.2 | D42: Were final deliverables, testing and acceptance records, turnover information, approved technical records, client signoffs, and other required closeout records completed and stored appropriately? | E42: Verify completion, approval, turnover, and proper storage of required final project records and deliverables. | F42: Scores final deliverable and acceptance records; do not duplicate broader administrative/financial closeout or lessons learned unless separately deficient. | Q42: =IF('Review Register'!M3="","",'Review Register'!M3) | R42: =IF('Review Register'!D3="","",'Review Register'!D3)
A43: Project ID 02-R01 | B43: Closeout / Lessons Learned | C43: 7.3 | D43: Were lessons learned captured during the project and consolidated at closeout into useful recommendations, with project-specific and quality-system improvement opportunities identified for follow-up where warranted? | E43: Verify that lessons learned are captured and converted into useful project-specific and quality-system improvement opportunities. | F43: Scores lessons learned and improvement capture; do not duplicate general closeout completion or final deliverable records unless separately deficient. | Q43: =IF('Review Register'!M3="","",'Review Register'!M3) | R43: =IF('Review Register'!D3="","",'Review Register'!D3)
A44: Project ID 03-R01 | B44: Project Record Accessibility / Organization | C44: 1.1 | D44: Are project records maintained in the Project Vault or another location permitted by the Project Vault SOP? | E44: Verify that material project records are stored in approved repositories with required traceability. | F44: Scores approved storage location and repository traceability; do not also score general findability or overall record quality unless a separate failure exists. | Q44: =IF('Review Register'!M4="","",'Review Register'!M4) | R44: =IF('Review Register'!D4="","",'Review Register'!D4)
A45: Project ID 03-R01 | B45: Project Record Accessibility / Organization | C45: 1.2 | D45: Are the project’s primary source records readily locatable so the reviewer can understand what was sold, how the project was established for execution, and where supporting QSR evidence is maintained? | E45: Verify that primary source records can be readily located and used to establish the project basis and supporting evidence. | F45: Scores findability and navigation; do not score the substantive quality of each underlying process record here. | Q45: =IF('Review Register'!M4="","",'Review Register'!M4) | R45: =IF('Review Register'!D4="","",'Review Register'!D4)
A46: Project ID 03-R01 | B46: Project Record Accessibility / Organization | C46: 1.3 | D46: Are project records organized, current, controlled, and sufficiently complete to support project execution, traceability, and reliable review? | E46: Verify the overall integrity, currency, control, and completeness of the project record for the lifecycle stage. | F46: Scores overall record integrity; do not duplicate isolated process-artifact failures unless they materially impair the overall project record. | Q46: =IF('Review Register'!M4="","",'Review Register'!M4) | R46: =IF('Review Register'!D4="","",'Review Register'!D4)
A47: Project ID 03-R01 | B47: Sales Handoff / Kickoff | C47: 2.1 | D47: Was Sales Handoff documented and effective in transferring the commercial, scope, schedule, budget, risk, client, and project-background information required by the PM and project team? | E47: Verify effective transfer of the information needed to move the project from sales/estimating into execution. | F47: Scores Sales Handoff; do not duplicate Internal Kickoff, Client Kickoff, or later project-planning controls unless separately deficient. | Q47: =IF('Review Register'!M4="","",'Review Register'!M4) | R47: =IF('Review Register'!D4="","",'Review Register'!D4)
A48: Project ID 03-R01 | B48: Sales Handoff / Kickoff | C48: 2.2 | D48: Was the Internal Kickoff documented and effective in aligning the project team on scope, schedule, budget, responsibilities, quality expectations, risks, and the execution approach? | E48: Verify internal project-team alignment before or at the start of execution. | F48: Scores Internal Kickoff alignment; do not duplicate the Sales Handoff transfer or Client Kickoff alignment unless separately deficient. | Q48: =IF('Review Register'!M4="","",'Review Register'!M4) | R48: =IF('Review Register'!D4="","",'Review Register'!D4)
A49: Project ID 03-R01 | B49: Sales Handoff / Kickoff | C49: 2.3 | D49: Was the Client Kickoff documented and effective in aligning ETG and the client on scope, deliverables, schedule, responsibilities, communications, quality, risks, dependencies, approvals, and success expectations? | E49: Verify alignment between ETG and the client on how the project will be executed and governed. | F49: Scores Client Kickoff alignment; do not duplicate Internal Kickoff or ongoing client communications and project reviews unless separately deficient. | Q49: =IF('Review Register'!M4="","",'Review Register'!M4) | R49: =IF('Review Register'!D4="","",'Review Register'!D4)
A50: Project ID 03-R01 | B50: Project Planning / Workbook Usage | C50: 3.1 | D50: Were all applicable PMLC project-management planning areas considered and appropriately tailored to the project’s size, complexity, risk, contract, and execution needs? | E50: Verify that project-management planning was completed and appropriately tailored to the project. | F50: Scores adequacy and tailoring of planning; do not duplicate Workbook maintenance or specific roles/communications controls unless separately deficient. | Q50: =IF('Review Register'!M4="","",'Review Register'!M4) | R50: =IF('Review Register'!D4="","",'Review Register'!D4)
A51: Project ID 03-R01 | B51: Project Planning / Workbook Usage | C51: 3.2 | D51: Were applicable Project Workbook components populated with sufficient, current, and usable information to support project execution, monitoring, and control? | E51: Verify that applicable Project Workbook components are populated and maintained as usable project-management records. | F51: Scores Workbook content and usability; do not duplicate the broader planning approach or specific risk/change controls unless separately deficient. | Q51: =IF('Review Register'!M4="","",'Review Register'!M4) | R51: =IF('Review Register'!D4="","",'Review Register'!D4)
A52: Project ID 03-R01 | B52: Project Planning / Workbook Usage | C52: 3.3 | D52: Were project roles, responsibilities, deliverables, stakeholder needs, communications, resources, and schedule commitments clearly established and maintained? | E52: Verify that the people, deliverables, communications, resources, and schedule commitments needed for execution are clearly established and maintained. | F52: Scores these execution-planning elements; do not duplicate general Workbook completeness or later review-cadence controls unless separately deficient. | Q52: =IF('Review Register'!M4="","",'Review Register'!M4) | R52: =IF('Review Register'!D4="","",'Review Register'!D4)
A53: Project ID 03-R01 | B53: Risk Management | C53: 4.1 | D53: Were material project risks identified, assessed, and documented at appropriate points beginning with estimating and Sales Handoff? | E53: Verify timely identification, assessment, and documentation of material project risks beginning before execution. | F53: Scores risk identification and assessment; do not duplicate Risk Registry usage or ongoing risk review/mitigation unless separately deficient. | Q53: =IF('Review Register'!M4="","",'Review Register'!M4) | R53: =IF('Review Register'!D4="","",'Review Register'!D4)
A54: Project ID 03-R01 | B54: Risk Management | C54: 4.2 | D54: Was the Project Workbook Risk Registry used and maintained, or was an acceptable equivalent clearly identified and traceable through the Project Workbook or project records? | E54: Verify use of the standard Risk Registry or a clearly identified, traceable acceptable equivalent. | F54: Scores the risk-recording mechanism and traceability; do not duplicate the quality of initial risk identification or ongoing risk management unless separately deficient. | Q54: =IF('Review Register'!M4="","",'Review Register'!M4) | R54: =IF('Review Register'!D4="","",'Review Register'!D4)
A55: Project ID 03-R01 | B55: Risk Management | C55: 4.3 | D55: Were risks reviewed throughout execution, with risk status, impacts, mitigation actions, owners, changes, and dispositions updated as warranted? | E55: Verify active management of identified risks throughout project execution. | F55: Scores ongoing risk review, mitigation, ownership, and disposition; do not duplicate initial risk identification or registry existence unless separately deficient. | Q55: =IF('Review Register'!M4="","",'Review Register'!M4) | R55: =IF('Review Register'!D4="","",'Review Register'!D4)
A56: Project ID 03-R01 | B56: Change Management | C56: 5.1 | D56: Were potential or actual changes to scope, schedule, budget, requirements, design, or other approved project baselines identified and documented when they arose? | E56: Verify that changes to approved project baselines are recognized and documented when they arise. | F56: Scores change identification and documentation; do not duplicate authorization/approval or incorporation of approved changes unless separately deficient. | Q56: =IF('Review Register'!M4="","",'Review Register'!M4) | R56: =IF('Review Register'!D4="","",'Review Register'!D4)
A57: Project ID 03-R01 | B57: Change Management | C57: 5.2 | D57: Were changes evaluated, communicated, authorized, and approved before out-of-scope or at-risk work proceeded, except where the contract expressly permitted another approach? | E57: Verify that changes are evaluated and appropriately authorized before affected work proceeds. | F57: Scores evaluation, communication, authorization, and approval; do not duplicate initial change identification or downstream record updates unless separately deficient. | Q57: =IF('Review Register'!M4="","",'Review Register'!M4) | R57: =IF('Review Register'!D4="","",'Review Register'!D4)
A58: Project ID 03-R01 | B58: Change Management | C58: 5.3 | D58: Were approved changes fully incorporated into applicable project-management, financial, schedule, technical, contractual, and client records? | E58: Verify that approved changes are fully incorporated into the records and baselines they affect. | F58: Scores implementation of approved changes into records; do not duplicate whether the change was identified or approved unless separately deficient. | Q58: =IF('Review Register'!M4="","",'Review Register'!M4) | R58: =IF('Review Register'!D4="","",'Review Register'!D4)
A59: Project ID 03-R01 | B59: Project Monitoring / Review Cadence | C59: 6.1 | D59: Were project reviews conducted at required or appropriate intervals, including applicable project checkpoints and recurring project reviews? | E59: Verify that project reviews and checkpoints occur at required or appropriate intervals. | F59: Scores review occurrence and cadence; do not duplicate the content of reviews or follow-through on resulting actions unless separately deficient. | Q59: =IF('Review Register'!M4="","",'Review Register'!M4) | R59: =IF('Review Register'!D4="","",'Review Register'!D4)
A60: Project ID 03-R01 | B60: Project Monitoring / Review Cadence | C60: 6.2 | D60: Did project reviews address current scope, schedule, budget and forecast, risks, changes, deliverables, quality, resources, client needs, and other material project conditions as applicable? | E60: Verify that project reviews address the material conditions needed to understand and control project performance. | F60: Scores review content and coverage; do not duplicate review cadence or action follow-through unless separately deficient. | Q60: =IF('Review Register'!M4="","",'Review Register'!M4) | R60: =IF('Review Register'!D4="","",'Review Register'!D4)
A61: Project ID 03-R01 | B61: Project Monitoring / Review Cadence | C61: 6.3 | D61: Were decisions, actions, owners, due dates, escalations, and follow-up resulting from project reviews documented and carried through? | E61: Verify that project-review decisions and actions are documented, assigned, escalated where needed, and followed through. | F61: Scores action management resulting from reviews; do not duplicate whether reviews occurred or what topics they covered unless separately deficient. | Q61: =IF('Review Register'!M4="","",'Review Register'!M4) | R61: =IF('Review Register'!D4="","",'Review Register'!D4)
A62: Project ID 03-R01 | B62: Closeout / Lessons Learned | C62: 7.1 | D62: Were applicable technical, administrative, financial, contractual, and client closeout activities completed and documented? | E62: Verify completion and documentation of the applicable overall project closeout activities. | F62: Scores overall closeout completion; do not duplicate specific deliverable/acceptance records or lessons learned unless separately deficient. | Q62: =IF('Review Register'!M4="","",'Review Register'!M4) | R62: =IF('Review Register'!D4="","",'Review Register'!D4)
A63: Project ID 03-R01 | B63: Closeout / Lessons Learned | C63: 7.2 | D63: Were final deliverables, testing and acceptance records, turnover information, approved technical records, client signoffs, and other required closeout records completed and stored appropriately? | E63: Verify completion, approval, turnover, and proper storage of required final project records and deliverables. | F63: Scores final deliverable and acceptance records; do not duplicate broader administrative/financial closeout or lessons learned unless separately deficient. | Q63: =IF('Review Register'!M4="","",'Review Register'!M4) | R63: =IF('Review Register'!D4="","",'Review Register'!D4)
A64: Project ID 03-R01 | B64: Closeout / Lessons Learned | C64: 7.3 | D64: Were lessons learned captured during the project and consolidated at closeout into useful recommendations, with project-specific and quality-system improvement opportunities identified for follow-up where warranted? | E64: Verify that lessons learned are captured and converted into useful project-specific and quality-system improvement opportunities. | F64: Scores lessons learned and improvement capture; do not duplicate general closeout completion or final deliverable records unless separately deficient. | Q64: =IF('Review Register'!M4="","",'Review Register'!M4) | R64: =IF('Review Register'!D4="","",'Review Register'!D4)
A65: Project ID 04-R01 | B65: Project Record Accessibility / Organization | C65: 1.1 | D65: Are project records maintained in the Project Vault or another location permitted by the Project Vault SOP? | E65: Verify that material project records are stored in approved repositories with required traceability. | F65: Scores approved storage location and repository traceability; do not also score general findability or overall record quality unless a separate failure exists. | Q65: =IF('Review Register'!M5="","",'Review Register'!M5) | R65: =IF('Review Register'!D5="","",'Review Register'!D5)
A66: Project ID 04-R01 | B66: Project Record Accessibility / Organization | C66: 1.2 | D66: Are the project’s primary source records readily locatable so the reviewer can understand what was sold, how the project was established for execution, and where supporting QSR evidence is maintained? | E66: Verify that primary source records can be readily located and used to establish the project basis and supporting evidence. | F66: Scores findability and navigation; do not score the substantive quality of each underlying process record here. | Q66: =IF('Review Register'!M5="","",'Review Register'!M5) | R66: =IF('Review Register'!D5="","",'Review Register'!D5)
A67: Project ID 04-R01 | B67: Project Record Accessibility / Organization | C67: 1.3 | D67: Are project records organized, current, controlled, and sufficiently complete to support project execution, traceability, and reliable review? | E67: Verify the overall integrity, currency, control, and completeness of the project record for the lifecycle stage. | F67: Scores overall record integrity; do not duplicate isolated process-artifact failures unless they materially impair the overall project record. | Q67: =IF('Review Register'!M5="","",'Review Register'!M5) | R67: =IF('Review Register'!D5="","",'Review Register'!D5)
A68: Project ID 04-R01 | B68: Sales Handoff / Kickoff | C68: 2.1 | D68: Was Sales Handoff documented and effective in transferring the commercial, scope, schedule, budget, risk, client, and project-background information required by the PM and project team? | E68: Verify effective transfer of the information needed to move the project from sales/estimating into execution. | F68: Scores Sales Handoff; do not duplicate Internal Kickoff, Client Kickoff, or later project-planning controls unless separately deficient. | Q68: =IF('Review Register'!M5="","",'Review Register'!M5) | R68: =IF('Review Register'!D5="","",'Review Register'!D5)
A69: Project ID 04-R01 | B69: Sales Handoff / Kickoff | C69: 2.2 | D69: Was the Internal Kickoff documented and effective in aligning the project team on scope, schedule, budget, responsibilities, quality expectations, risks, and the execution approach? | E69: Verify internal project-team alignment before or at the start of execution. | F69: Scores Internal Kickoff alignment; do not duplicate the Sales Handoff transfer or Client Kickoff alignment unless separately deficient. | Q69: =IF('Review Register'!M5="","",'Review Register'!M5) | R69: =IF('Review Register'!D5="","",'Review Register'!D5)
A70: Project ID 04-R01 | B70: Sales Handoff / Kickoff | C70: 2.3 | D70: Was the Client Kickoff documented and effective in aligning ETG and the client on scope, deliverables, schedule, responsibilities, communications, quality, risks, dependencies, approvals, and success expectations? | E70: Verify alignment between ETG and the client on how the project will be executed and governed. | F70: Scores Client Kickoff alignment; do not duplicate Internal Kickoff or ongoing client communications and project reviews unless separately deficient. | Q70: =IF('Review Register'!M5="","",'Review Register'!M5) | R70: =IF('Review Register'!D5="","",'Review Register'!D5)
A71: Project ID 04-R01 | B71: Project Planning / Workbook Usage | C71: 3.1 | D71: Were all applicable PMLC project-management planning areas considered and appropriately tailored to the project’s size, complexity, risk, contract, and execution needs? | E71: Verify that project-management planning was completed and appropriately tailored to the project. | F71: Scores adequacy and tailoring of planning; do not duplicate Workbook maintenance or specific roles/communications controls unless separately deficient. | Q71: =IF('Review Register'!M5="","",'Review Register'!M5) | R71: =IF('Review Register'!D5="","",'Review Register'!D5)
A72: Project ID 04-R01 | B72: Project Planning / Workbook Usage | C72: 3.2 | D72: Were applicable Project Workbook components populated with sufficient, current, and usable information to support project execution, monitoring, and control? | E72: Verify that applicable Project Workbook components are populated and maintained as usable project-management records. | F72: Scores Workbook content and usability; do not duplicate the broader planning approach or specific risk/change controls unless separately deficient. | Q72: =IF('Review Register'!M5="","",'Review Register'!M5) | R72: =IF('Review Register'!D5="","",'Review Register'!D5)
A73: Project ID 04-R01 | B73: Project Planning / Workbook Usage | C73: 3.3 | D73: Were project roles, responsibilities, deliverables, stakeholder needs, communications, resources, and schedule commitments clearly established and maintained? | E73: Verify that the people, deliverables, communications, resources, and schedule commitments needed for execution are clearly established and maintained. | F73: Scores these execution-planning elements; do not duplicate general Workbook completeness or later review-cadence controls unless separately deficient. | Q73: =IF('Review Register'!M5="","",'Review Register'!M5) | R73: =IF('Review Register'!D5="","",'Review Register'!D5)
A74: Project ID 04-R01 | B74: Risk Management | C74: 4.1 | D74: Were material project risks identified, assessed, and documented at appropriate points beginning with estimating and Sales Handoff? | E74: Verify timely identification, assessment, and documentation of material project risks beginning before execution. | F74: Scores risk identification and assessment; do not duplicate Risk Registry usage or ongoing risk review/mitigation unless separately deficient. | Q74: =IF('Review Register'!M5="","",'Review Register'!M5) | R74: =IF('Review Register'!D5="","",'Review Register'!D5)
A75: Project ID 04-R01 | B75: Risk Management | C75: 4.2 | D75: Was the Project Workbook Risk Registry used and maintained, or was an acceptable equivalent clearly identified and traceable through the Project Workbook or project records? | E75: Verify use of the standard Risk Registry or a clearly identified, traceable acceptable equivalent. | F75: Scores the risk-recording mechanism and traceability; do not duplicate the quality of initial risk identification or ongoing risk management unless separately deficient. | Q75: =IF('Review Register'!M5="","",'Review Register'!M5) | R75: =IF('Review Register'!D5="","",'Review Register'!D5)
A76: Project ID 04-R01 | B76: Risk Management | C76: 4.3 | D76: Were risks reviewed throughout execution, with risk status, impacts, mitigation actions, owners, changes, and dispositions updated as warranted? | E76: Verify active management of identified risks throughout project execution. | F76: Scores ongoing risk review, mitigation, ownership, and disposition; do not duplicate initial risk identification or registry existence unless separately deficient. | Q76: =IF('Review Register'!M5="","",'Review Register'!M5) | R76: =IF('Review Register'!D5="","",'Review Register'!D5)
A77: Project ID 04-R01 | B77: Change Management | C77: 5.1 | D77: Were potential or actual changes to scope, schedule, budget, requirements, design, or other approved project baselines identified and documented when they arose? | E77: Verify that changes to approved project baselines are recognized and documented when they arise. | F77: Scores change identification and documentation; do not duplicate authorization/approval or incorporation of approved changes unless separately deficient. | Q77: =IF('Review Register'!M5="","",'Review Register'!M5) | R77: =IF('Review Register'!D5="","",'Review Register'!D5)
A78: Project ID 04-R01 | B78: Change Management | C78: 5.2 | D78: Were changes evaluated, communicated, authorized, and approved before out-of-scope or at-risk work proceeded, except where the contract expressly permitted another approach? | E78: Verify that changes are evaluated and appropriately authorized before affected work proceeds. | F78: Scores evaluation, communication, authorization, and approval; do not duplicate initial change identification or downstream record updates unless separately deficient. | Q78: =IF('Review Register'!M5="","",'Review Register'!M5) | R78: =IF('Review Register'!D5="","",'Review Register'!D5)
A79: Project ID 04-R01 | B79: Change Management | C79: 5.3 | D79: Were approved changes fully incorporated into applicable project-management, financial, schedule, technical, contractual, and client records? | E79: Verify that approved changes are fully incorporated into the records and baselines they affect. | F79: Scores implementation of approved changes into records; do not duplicate whether the change was identified or approved unless separately deficient. | Q79: =IF('Review Register'!M5="","",'Review Register'!M5) | R79: =IF('Review Register'!D5="","",'Review Register'!D5)
A80: Project ID 04-R01 | B80: Project Monitoring / Review Cadence | C80: 6.1 | D80: Were project reviews conducted at required or appropriate intervals, including applicable project checkpoints and recurring project reviews? | E80: Verify that project reviews and checkpoints occur at required or appropriate intervals. | F80: Scores review occurrence and cadence; do not duplicate the content of reviews or follow-through on resulting actions unless separately deficient. | Q80: =IF('Review Register'!M5="","",'Review Register'!M5) | R80: =IF('Review Register'!D5="","",'Review Register'!D5)
A81: Project ID 04-R01 | B81: Project Monitoring / Review Cadence | C81: 6.2 | D81: Did project reviews address current scope, schedule, budget and forecast, risks, changes, deliverables, quality, resources, client needs, and other material project conditions as applicable? | E81: Verify that project reviews address the material conditions needed to understand and control project performance. | F81: Scores review content and coverage; do not duplicate review cadence or action follow-through unless separately deficient. | Q81: =IF('Review Register'!M5="","",'Review Register'!M5) | R81: =IF('Review Register'!D5="","",'Review Register'!D5)
A82: Project ID 04-R01 | B82: Project Monitoring / Review Cadence | C82: 6.3 | D82: Were decisions, actions, owners, due dates, escalations, and follow-up resulting from project reviews documented and carried through? | E82: Verify that project-review decisions and actions are documented, assigned, escalated where needed, and followed through. | F82: Scores action management resulting from reviews; do not duplicate whether reviews occurred or what topics they covered unless separately deficient. | Q82: =IF('Review Register'!M5="","",'Review Register'!M5) | R82: =IF('Review Register'!D5="","",'Review Register'!D5)
A83: Project ID 04-R01 | B83: Closeout / Lessons Learned | C83: 7.1 | D83: Were applicable technical, administrative, financial, contractual, and client closeout activities completed and documented? | E83: Verify completion and documentation of the applicable overall project closeout activities. | F83: Scores overall closeout completion; do not duplicate specific deliverable/acceptance records or lessons learned unless separately deficient. | Q83: =IF('Review Register'!M5="","",'Review Register'!M5) | R83: =IF('Review Register'!D5="","",'Review Register'!D5)
A84: Project ID 04-R01 | B84: Closeout / Lessons Learned | C84: 7.2 | D84: Were final deliverables, testing and acceptance records, turnover information, approved technical records, client signoffs, and other required closeout records completed and stored appropriately? | E84: Verify completion, approval, turnover, and proper storage of required final project records and deliverables. | F84: Scores final deliverable and acceptance records; do not duplicate broader administrative/financial closeout or lessons learned unless separately deficient. | Q84: =IF('Review Register'!M5="","",'Review Register'!M5) | R84: =IF('Review Register'!D5="","",'Review Register'!D5)
A85: Project ID 04-R01 | B85: Closeout / Lessons Learned | C85: 7.3 | D85: Were lessons learned captured during the project and consolidated at closeout into useful recommendations, with project-specific and quality-system improvement opportunities identified for follow-up where warranted? | E85: Verify that lessons learned are captured and converted into useful project-specific and quality-system improvement opportunities. | F85: Scores lessons learned and improvement capture; do not duplicate general closeout completion or final deliverable records unless separately deficient. | Q85: =IF('Review Register'!M5="","",'Review Register'!M5) | R85: =IF('Review Register'!D5="","",'Review Register'!D5)
A86: Project ID 05-R01 | B86: Project Record Accessibility / Organization | C86: 1.1 | D86: Are project records maintained in the Project Vault or another location permitted by the Project Vault SOP? | E86: Verify that material project records are stored in approved repositories with required traceability. | F86: Scores approved storage location and repository traceability; do not also score general findability or overall record quality unless a separate failure exists. | Q86: =IF('Review Register'!M6="","",'Review Register'!M6) | R86: =IF('Review Register'!D6="","",'Review Register'!D6)
A87: Project ID 05-R01 | B87: Project Record Accessibility / Organization | C87: 1.2 | D87: Are the project’s primary source records readily locatable so the reviewer can understand what was sold, how the project was established for execution, and where supporting QSR evidence is maintained? | E87: Verify that primary source records can be readily located and used to establish the project basis and supporting evidence. | F87: Scores findability and navigation; do not score the substantive quality of each underlying process record here. | Q87: =IF('Review Register'!M6="","",'Review Register'!M6) | R87: =IF('Review Register'!D6="","",'Review Register'!D6)
A88: Project ID 05-R01 | B88: Project Record Accessibility / Organization | C88: 1.3 | D88: Are project records organized, current, controlled, and sufficiently complete to support project execution, traceability, and reliable review? | E88: Verify the overall integrity, currency, control, and completeness of the project record for the lifecycle stage. | F88: Scores overall record integrity; do not duplicate isolated process-artifact failures unless they materially impair the overall project record. | Q88: =IF('Review Register'!M6="","",'Review Register'!M6) | R88: =IF('Review Register'!D6="","",'Review Register'!D6)
A89: Project ID 05-R01 | B89: Sales Handoff / Kickoff | C89: 2.1 | D89: Was Sales Handoff documented and effective in transferring the commercial, scope, schedule, budget, risk, client, and project-background information required by the PM and project team? | E89: Verify effective transfer of the information needed to move the project from sales/estimating into execution. | F89: Scores Sales Handoff; do not duplicate Internal Kickoff, Client Kickoff, or later project-planning controls unless separately deficient. | Q89: =IF('Review Register'!M6="","",'Review Register'!M6) | R89: =IF('Review Register'!D6="","",'Review Register'!D6)
A90: Project ID 05-R01 | B90: Sales Handoff / Kickoff | C90: 2.2 | D90: Was the Internal Kickoff documented and effective in aligning the project team on scope, schedule, budget, responsibilities, quality expectations, risks, and the execution approach? | E90: Verify internal project-team alignment before or at the start of execution. | F90: Scores Internal Kickoff alignment; do not duplicate the Sales Handoff transfer or Client Kickoff alignment unless separately deficient. | Q90: =IF('Review Register'!M6="","",'Review Register'!M6) | R90: =IF('Review Register'!D6="","",'Review Register'!D6)
A91: Project ID 05-R01 | B91: Sales Handoff / Kickoff | C91: 2.3 | D91: Was the Client Kickoff documented and effective in aligning ETG and the client on scope, deliverables, schedule, responsibilities, communications, quality, risks, dependencies, approvals, and success expectations? | E91: Verify alignment between ETG and the client on how the project will be executed and governed. | F91: Scores Client Kickoff alignment; do not duplicate Internal Kickoff or ongoing client communications and project reviews unless separately deficient. | Q91: =IF('Review Register'!M6="","",'Review Register'!M6) | R91: =IF('Review Register'!D6="","",'Review Register'!D6)
A92: Project ID 05-R01 | B92: Project Planning / Workbook Usage | C92: 3.1 | D92: Were all applicable PMLC project-management planning areas considered and appropriately tailored to the project’s size, complexity, risk, contract, and execution needs? | E92: Verify that project-management planning was completed and appropriately tailored to the project. | F92: Scores adequacy and tailoring of planning; do not duplicate Workbook maintenance or specific roles/communications controls unless separately deficient. | Q92: =IF('Review Register'!M6="","",'Review Register'!M6) | R92: =IF('Review Register'!D6="","",'Review Register'!D6)
A93: Project ID 05-R01 | B93: Project Planning / Workbook Usage | C93: 3.2 | D93: Were applicable Project Workbook components populated with sufficient, current, and usable information to support project execution, monitoring, and control? | E93: Verify that applicable Project Workbook components are populated and maintained as usable project-management records. | F93: Scores Workbook content and usability; do not duplicate the broader planning approach or specific risk/change controls unless separately deficient. | Q93: =IF('Review Register'!M6="","",'Review Register'!M6) | R93: =IF('Review Register'!D6="","",'Review Register'!D6)
A94: Project ID 05-R01 | B94: Project Planning / Workbook Usage | C94: 3.3 | D94: Were project roles, responsibilities, deliverables, stakeholder needs, communications, resources, and schedule commitments clearly established and maintained? | E94: Verify that the people, deliverables, communications, resources, and schedule commitments needed for execution are clearly established and maintained. | F94: Scores these execution-planning elements; do not duplicate general Workbook completeness or later review-cadence controls unless separately deficient. | Q94: =IF('Review Register'!M6="","",'Review Register'!M6) | R94: =IF('Review Register'!D6="","",'Review Register'!D6)
A95: Project ID 05-R01 | B95: Risk Management | C95: 4.1 | D95: Were material project risks identified, assessed, and documented at appropriate points beginning with estimating and Sales Handoff? | E95: Verify timely identification, assessment, and documentation of material project risks beginning before execution. | F95: Scores risk identification and assessment; do not duplicate Risk Registry usage or ongoing risk review/mitigation unless separately deficient. | Q95: =IF('Review Register'!M6="","",'Review Register'!M6) | R95: =IF('Review Register'!D6="","",'Review Register'!D6)
A96: Project ID 05-R01 | B96: Risk Management | C96: 4.2 | D96: Was the Project Workbook Risk Registry used and maintained, or was an acceptable equivalent clearly identified and traceable through the Project Workbook or project records? | E96: Verify use of the standard Risk Registry or a clearly identified, traceable acceptable equivalent. | F96: Scores the risk-recording mechanism and traceability; do not duplicate the quality of initial risk identification or ongoing risk management unless separately deficient. | Q96: =IF('Review Register'!M6="","",'Review Register'!M6) | R96: =IF('Review Register'!D6="","",'Review Register'!D6)
A97: Project ID 05-R01 | B97: Risk Management | C97: 4.3 | D97: Were risks reviewed throughout execution, with risk status, impacts, mitigation actions, owners, changes, and dispositions updated as warranted? | E97: Verify active management of identified risks throughout project execution. | F97: Scores ongoing risk review, mitigation, ownership, and disposition; do not duplicate initial risk identification or registry existence unless separately deficient. | Q97: =IF('Review Register'!M6="","",'Review Register'!M6) | R97: =IF('Review Register'!D6="","",'Review Register'!D6)
A98: Project ID 05-R01 | B98: Change Management | C98: 5.1 | D98: Were potential or actual changes to scope, schedule, budget, requirements, design, or other approved project baselines identified and documented when they arose? | E98: Verify that changes to approved project baselines are recognized and documented when they arise. | F98: Scores change identification and documentation; do not duplicate authorization/approval or incorporation of approved changes unless separately deficient. | Q98: =IF('Review Register'!M6="","",'Review Register'!M6) | R98: =IF('Review Register'!D6="","",'Review Register'!D6)
A99: Project ID 05-R01 | B99: Change Management | C99: 5.2 | D99: Were changes evaluated, communicated, authorized, and approved before out-of-scope or at-risk work proceeded, except where the contract expressly permitted another approach? | E99: Verify that changes are evaluated and appropriately authorized before affected work proceeds. | F99: Scores evaluation, communication, authorization, and approval; do not duplicate initial change identification or downstream record updates unless separately deficient. | Q99: =IF('Review Register'!M6="","",'Review Register'!M6) | R99: =IF('Review Register'!D6="","",'Review Register'!D6)
A100: Project ID 05-R01 | B100: Change Management | C100: 5.3 | D100: Were approved changes fully incorporated into applicable project-management, financial, schedule, technical, contractual, and client records? | E100: Verify that approved changes are fully incorporated into the records and baselines they affect. | F100: Scores implementation of approved changes into records; do not duplicate whether the change was identified or approved unless separately deficient. | Q100: =IF('Review Register'!M6="","",'Review Register'!M6) | R100: =IF('Review Register'!D6="","",'Review Register'!D6)
...

Sheet Review Entry
A1: Review ID | B1: Review Area | C1: Question ID | D1: Controlled Question Text | E1: Primary Intent | F1: Result | G1: Evidence Status | H1: Evidence Reviewed / Location | I1: PM Clarification Used? | J1: PM Clarification Summary | K1: Reviewer Observation | L1: Primary Root Cause | M1: Root-Cause Explanation | N1: Follow-Up Required? | O1: Reviewer | P1: Project Manager
A2: Project ID 01-R01 | B2: Project Record Accessibility / Organization | C2: 1.1 | D2: Are project records maintained in the Project Vault or another location permitted by the Project Vault SOP? | E2: Verify that material project records are stored in approved repositories with required traceability. | O2: =IF('Review Register'!M2="","",'Review Register'!M2) | P2: =IF('Review Register'!D2="","",'Review Register'!D2)
A3: Project ID 01-R01 | B3: Project Record Accessibility / Organization | C3: 1.2 | D3: Are the project’s primary source records readily locatable so the reviewer can understand what was sold, how the project was established for execution, and where supporting QSR evidence is maintained? | E3: Verify that primary source records can be readily located and used to establish the project basis and supporting evidence. | O3: =IF('Review Register'!M2="","",'Review Register'!M2) | P3: =IF('Review Register'!D2="","",'Review Register'!D2)
A4: Project ID 01-R01 | B4: Project Record Accessibility / Organization | C4: 1.3 | D4: Are project records organized, current, controlled, and sufficiently complete to support project execution, traceability, and reliable review? | E4: Verify the overall integrity, currency, control, and completeness of the project record for the lifecycle stage. | O4: =IF('Review Register'!M2="","",'Review Register'!M2) | P4: =IF('Review Register'!D2="","",'Review Register'!D2)
A5: Project ID 01-R01 | B5: Sales Handoff / Kickoff | C5: 2.1 | D5: Was Sales Handoff documented and effective in transferring the commercial, scope, schedule, budget, risk, client, and project-background information required by the PM and project team? | E5: Verify effective transfer of the information needed to move the project from sales/estimating into execution. | O5: =IF('Review Register'!M2="","",'Review Register'!M2) | P5: =IF('Review Register'!D2="","",'Review Register'!D2)
A6: Project ID 01-R01 | B6: Sales Handoff / Kickoff | C6: 2.2 | D6: Was the Internal Kickoff documented and effective in aligning the project team on scope, schedule, budget, responsibilities, quality expectations, risks, and the execution approach? | E6: Verify internal project-team alignment before or at the start of execution. | O6: =IF('Review Register'!M2="","",'Review Register'!M2) | P6: =IF('Review Register'!D2="","",'Review Register'!D2)
A7: Project ID 01-R01 | B7: Sales Handoff / Kickoff | C7: 2.3 | D7: Was the Client Kickoff documented and effective in aligning ETG and the client on scope, deliverables, schedule, responsibilities, communications, quality, risks, dependencies, approvals, and success expectations? | E7: Verify alignment between ETG and the client on how the project will be executed and governed. | O7: =IF('Review Register'!M2="","",'Review Register'!M2) | P7: =IF('Review Register'!D2="","",'Review Register'!D2)
A8: Project ID 01-R01 | B8: Project Planning / Workbook Usage | C8: 3.1 | D8: Were all applicable PMLC project-management planning areas considered and appropriately tailored to the project’s size, complexity, risk, contract, and execution needs? | E8: Verify that all applicable PMLC project-management planning areas were considered and appropriately tailored to the project. | O8: =IF('Review Register'!M2="","",'Review Register'!M2) | P8: =IF('Review Register'!D2="","",'Review Register'!D2)
A9: Project ID 01-R01 | B9: Project Planning / Workbook Usage | C9: 3.2 | D9: Were applicable Project Workbook components used and sufficiently populated to provide the required project-management records? | E9: Verify that applicable Project Workbook components supporting the Project Management Plan are used and sufficiently populated to serve as the intended project-management records. | O9: =IF('Review Register'!M2="","",'Review Register'!M2) | P9: =IF('Review Register'!D2="","",'Review Register'!D2)
A10: Project ID 01-R01 | B10: Project Planning / Workbook Usage | C10: 3.3 | D10: Were applicable project roles, responsibilities, deliverables, stakeholder needs, communications, resources, and schedule commitments clearly established and maintained? | E10: Verify that applicable roles and responsibilities, deliverables, stakeholder needs, communications, resources, and schedule commitments are established and maintained to support project execution. | O10: =IF('Review Register'!M2="","",'Review Register'!M2) | P10: =IF('Review Register'!D2="","",'Review Register'!D2)
A11: Project ID 01-R01 | B11: Risk Management | C11: 4.1 | D11: Were material project risks identified, assessed, and documented at appropriate points beginning with estimating and Sales Handoff? | E11: Verify that material project risks are identified and assessed at appropriate stages and that applicable pre-execution risks are carried forward into project planning. | O11: =IF('Review Register'!M2="","",'Review Register'!M2) | P11: =IF('Review Register'!D2="","",'Review Register'!D2)
A12: Project ID 01-R01 | B12: Risk Management | C12: 4.2 | D12: Was the Project Workbook Risk Registry used and maintained, or was an acceptable equivalent clearly identified and traceable through the Project Workbook or project records? | E12: Verify use of the standard Risk Registry or a clearly identified, traceable acceptable equivalent. | O12: =IF('Review Register'!M2="","",'Review Register'!M2) | P12: =IF('Review Register'!D2="","",'Review Register'!D2)
A13: Project ID 01-R01 | B13: Risk Management | C13: 4.3 | D13: Were risks reviewed throughout execution, with risk status, impacts, mitigation actions, owners, changes, and dispositions updated as warranted? | E13: Verify active management of identified risks throughout project execution. | O13: =IF('Review Register'!M2="","",'Review Register'!M2) | P13: =IF('Review Register'!D2="","",'Review Register'!D2)
A14: Project ID 01-R01 | B14: Change Management | C14: 5.1 | D14: Were potential or actual changes to scope, schedule, budget, requirements, design, or other approved project baselines identified and documented when they arose? | E14: Verify that material potential or actual changes to approved project baselines are recognized and documented when they arise. | O14: =IF('Review Register'!M2="","",'Review Register'!M2) | P14: =IF('Review Register'!D2="","",'Review Register'!D2)
A15: Project ID 01-R01 | B15: Change Management | C15: 5.2 | D15: Were changes evaluated, communicated, authorized, and approved before out-of-scope or at-risk work proceeded, except where the contract expressly permitted another approach? | E15: Verify that changes are evaluated and appropriately authorized before affected work proceeds. | O15: =IF('Review Register'!M2="","",'Review Register'!M2) | P15: =IF('Review Register'!D2="","",'Review Register'!D2)
A16: Project ID 01-R01 | B16: Change Management | C16: 5.3 | D16: Were approved changes fully incorporated into applicable project-management, financial, schedule, technical, contractual, and client records? | E16: Verify that approved changes are fully incorporated into the records and baselines they affect. | O16: =IF('Review Register'!M2="","",'Review Register'!M2) | P16: =IF('Review Register'!D2="","",'Review Register'!D2)
A17: Project ID 01-R01 | B17: Project Monitoring / Review Cadence | C17: 6.1 | D17: Were project reviews conducted at required or appropriate intervals, including applicable project checkpoints and recurring project reviews? | E17: Verify that project reviews and checkpoints occur at required or appropriate intervals. | O17: =IF('Review Register'!M2="","",'Review Register'!M2) | P17: =IF('Review Register'!D2="","",'Review Register'!D2)
A18: Project ID 01-R01 | B18: Project Monitoring / Review Cadence | C18: 6.2 | D18: Did project reviews address current scope, schedule, budget and forecast, risks, changes, deliverables, quality, resources, client needs, and other material project conditions as applicable? | E18: Verify that project reviews address the material conditions needed to understand and control project performance. | O18: =IF('Review Register'!M2="","",'Review Register'!M2) | P18: =IF('Review Register'!D2="","",'Review Register'!D2)
A19: Project ID 01-R01 | B19: Project Monitoring / Review Cadence | C19: 6.3 | D19: Were decisions, actions, owners, due dates, escalations, and follow-up resulting from project reviews documented and carried through? | E19: Verify that project-review decisions and actions are documented, assigned, escalated where needed, and followed through. | O19: =IF('Review Register'!M2="","",'Review Register'!M2) | P19: =IF('Review Register'!D2="","",'Review Register'!D2)
A20: Project ID 01-R01 | B20: Closeout / Lessons Learned | C20: 7.1 | D20: Were applicable technical, administrative, financial, contractual, and client closeout activities completed and documented? | E20: Verify completion and documentation of the applicable overall project closeout activities. | O20: =IF('Review Register'!M2="","",'Review Register'!M2) | P20: =IF('Review Register'!D2="","",'Review Register'!D2)
A21: Project ID 01-R01 | B21: Closeout / Lessons Learned | C21: 7.2 | D21: Were final deliverables, testing and acceptance records, turnover information, approved technical records, client signoffs, and other required closeout records completed and stored appropriately? | E21: Verify completion, approval, turnover, and proper storage of required final project records and deliverables. | O21: =IF('Review Register'!M2="","",'Review Register'!M2) | P21: =IF('Review Register'!D2="","",'Review Register'!D2)
A22: Project ID 01-R01 | B22: Closeout / Lessons Learned | C22: 7.3 | D22: Were lessons learned captured during the project and consolidated at closeout into useful recommendations, with project-specific and quality-system improvement opportunities identified for follow-up where warranted? | E22: Verify that lessons learned are captured and converted into useful project-specific and quality-system improvement opportunities. | O22: =IF('Review Register'!M2="","",'Review Register'!M2) | P22: =IF('Review Register'!D2="","",'Review Register'!D2)
A23: Project ID 02-R01 | B23: Project Record Accessibility / Organization | C23: 1.1 | D23: Are project records maintained in the Project Vault or another location permitted by the Project Vault SOP? | E23: Verify that material project records are stored in approved repositories with required traceability. | O23: =IF('Review Register'!M3="","",'Review Register'!M3) | P23: =IF('Review Register'!D3="","",'Review Register'!D3)
A24: Project ID 02-R01 | B24: Project Record Accessibility / Organization | C24: 1.2 | D24: Are the project’s primary source records readily locatable so the reviewer can understand what was sold, how the project was established for execution, and where supporting QSR evidence is maintained? | E24: Verify that primary source records can be readily located and used to establish the project basis and supporting evidence. | O24: =IF('Review Register'!M3="","",'Review Register'!M3) | P24: =IF('Review Register'!D3="","",'Review Register'!D3)
A25: Project ID 02-R01 | B25: Project Record Accessibility / Organization | C25: 1.3 | D25: Are project records organized, current, controlled, and sufficiently complete to support project execution, traceability, and reliable review? | E25: Verify the overall integrity, currency, control, and completeness of the project record for the lifecycle stage. | O25: =IF('Review Register'!M3="","",'Review Register'!M3) | P25: =IF('Review Register'!D3="","",'Review Register'!D3)
A26: Project ID 02-R01 | B26: Sales Handoff / Kickoff | C26: 2.1 | D26: Was Sales Handoff documented and effective in transferring the commercial, scope, schedule, budget, risk, client, and project-background information required by the PM and project team? | E26: Verify effective transfer of the information needed to move the project from sales/estimating into execution. | O26: =IF('Review Register'!M3="","",'Review Register'!M3) | P26: =IF('Review Register'!D3="","",'Review Register'!D3)
A27: Project ID 02-R01 | B27: Sales Handoff / Kickoff | C27: 2.2 | D27: Was the Internal Kickoff documented and effective in aligning the project team on scope, schedule, budget, responsibilities, quality expectations, risks, and the execution approach? | E27: Verify internal project-team alignment before or at the start of execution. | O27: =IF('Review Register'!M3="","",'Review Register'!M3) | P27: =IF('Review Register'!D3="","",'Review Register'!D3)
A28: Project ID 02-R01 | B28: Sales Handoff / Kickoff | C28: 2.3 | D28: Was the Client Kickoff documented and effective in aligning ETG and the client on scope, deliverables, schedule, responsibilities, communications, quality, risks, dependencies, approvals, and success expectations? | E28: Verify alignment between ETG and the client on how the project will be executed and governed. | O28: =IF('Review Register'!M3="","",'Review Register'!M3) | P28: =IF('Review Register'!D3="","",'Review Register'!D3)
A29: Project ID 02-R01 | B29: Project Planning / Workbook Usage | C29: 3.1 | D29: Were all applicable PMLC project-management planning areas considered and appropriately tailored to the project’s size, complexity, risk, contract, and execution needs? | E29: Verify that all applicable PMLC project-management planning areas were considered and appropriately tailored to the project. | O29: =IF('Review Register'!M3="","",'Review Register'!M3) | P29: =IF('Review Register'!D3="","",'Review Register'!D3)
A30: Project ID 02-R01 | B30: Project Planning / Workbook Usage | C30: 3.2 | D30: Were applicable Project Workbook components used and sufficiently populated to provide the required project-management records? | E30: Verify that applicable Project Workbook components supporting the Project Management Plan are used and sufficiently populated to serve as the intended project-management records. | O30: =IF('Review Register'!M3="","",'Review Register'!M3) | P30: =IF('Review Register'!D3="","",'Review Register'!D3)
A31: Project ID 02-R01 | B31: Project Planning / Workbook Usage | C31: 3.3 | D31: Were applicable project roles, responsibilities, deliverables, stakeholder needs, communications, resources, and schedule commitments clearly established and maintained? | E31: Verify that applicable roles and responsibilities, deliverables, stakeholder needs, communications, resources, and schedule commitments are established and maintained to support project execution. | O31: =IF('Review Register'!M3="","",'Review Register'!M3) | P31: =IF('Review Register'!D3="","",'Review Register'!D3)
A32: Project ID 02-R01 | B32: Risk Management | C32: 4.1 | D32: Were material project risks identified, assessed, and documented at appropriate points beginning with estimating and Sales Handoff? | E32: Verify that material project risks are identified and assessed at appropriate stages and that applicable pre-execution risks are carried forward into project planning. | O32: =IF('Review Register'!M3="","",'Review Register'!M3) | P32: =IF('Review Register'!D3="","",'Review Register'!D3)
A33: Project ID 02-R01 | B33: Risk Management | C33: 4.2 | D33: Was the Project Workbook Risk Registry used and maintained, or was an acceptable equivalent clearly identified and traceable through the Project Workbook or project records? | E33: Verify use of the standard Risk Registry or a clearly identified, traceable acceptable equivalent. | O33: =IF('Review Register'!M3="","",'Review Register'!M3) | P33: =IF('Review Register'!D3="","",'Review Register'!D3)
A34: Project ID 02-R01 | B34: Risk Management | C34: 4.3 | D34: Were risks reviewed throughout execution, with risk status, impacts, mitigation actions, owners, changes, and dispositions updated as warranted? | E34: Verify active management of identified risks throughout project execution. | O34: =IF('Review Register'!M3="","",'Review Register'!M3) | P34: =IF('Review Register'!D3="","",'Review Register'!D3)
A35: Project ID 02-R01 | B35: Change Management | C35: 5.1 | D35: Were potential or actual changes to scope, schedule, budget, requirements, design, or other approved project baselines identified and documented when they arose? | E35: Verify that material potential or actual changes to approved project baselines are recognized and documented when they arise. | O35: =IF('Review Register'!M3="","",'Review Register'!M3) | P35: =IF('Review Register'!D3="","",'Review Register'!D3)
A36: Project ID 02-R01 | B36: Change Management | C36: 5.2 | D36: Were changes evaluated, communicated, authorized, and approved before out-of-scope or at-risk work proceeded, except where the contract expressly permitted another approach? | E36: Verify that changes are evaluated and appropriately authorized before affected work proceeds. | O36: =IF('Review Register'!M3="","",'Review Register'!M3) | P36: =IF('Review Register'!D3="","",'Review Register'!D3)
A37: Project ID 02-R01 | B37: Change Management | C37: 5.3 | D37: Were approved changes fully incorporated into applicable project-management, financial, schedule, technical, contractual, and client records? | E37: Verify that approved changes are fully incorporated into the records and baselines they affect. | O37: =IF('Review Register'!M3="","",'Review Register'!M3) | P37: =IF('Review Register'!D3="","",'Review Register'!D3)
A38: Project ID 02-R01 | B38: Project Monitoring / Review Cadence | C38: 6.1 | D38: Were project reviews conducted at required or appropriate intervals, including applicable project checkpoints and recurring project reviews? | E38: Verify that project reviews and checkpoints occur at required or appropriate intervals. | O38: =IF('Review Register'!M3="","",'Review Register'!M3) | P38: =IF('Review Register'!D3="","",'Review Register'!D3)
A39: Project ID 02-R01 | B39: Project Monitoring / Review Cadence | C39: 6.2 | D39: Did project reviews address current scope, schedule, budget and forecast, risks, changes, deliverables, quality, resources, client needs, and other material project conditions as applicable? | E39: Verify that project reviews address the material conditions needed to understand and control project performance. | O39: =IF('Review Register'!M3="","",'Review Register'!M3) | P39: =IF('Review Register'!D3="","",'Review Register'!D3)
A40: Project ID 02-R01 | B40: Project Monitoring / Review Cadence | C40: 6.3 | D40: Were decisions, actions, owners, due dates, escalations, and follow-up resulting from project reviews documented and carried through? | E40: Verify that project-review decisions and actions are documented, assigned, escalated where needed, and followed through. | O40: =IF('Review Register'!M3="","",'Review Register'!M3) | P40: =IF('Review Register'!D3="","",'Review Register'!D3)
A41: Project ID 02-R01 | B41: Closeout / Lessons Learned | C41: 7.1 | D41: Were applicable technical, administrative, financial, contractual, and client closeout activities completed and documented? | E41: Verify completion and documentation of the applicable overall project closeout activities. | O41: =IF('Review Register'!M3="","",'Review Register'!M3) | P41: =IF('Review Register'!D3="","",'Review Register'!D3)
A42: Project ID 02-R01 | B42: Closeout / Lessons Learned | C42: 7.2 | D42: Were final deliverables, testing and acceptance records, turnover information, approved technical records, client signoffs, and other required closeout records completed and stored appropriately? | E42: Verify completion, approval, turnover, and proper storage of required final project records and deliverables. | O42: =IF('Review Register'!M3="","",'Review Register'!M3) | P42: =IF('Review Register'!D3="","",'Review Register'!D3)
A43: Project ID 02-R01 | B43: Closeout / Lessons Learned | C43: 7.3 | D43: Were lessons learned captured during the project and consolidated at closeout into useful recommendations, with project-specific and quality-system improvement opportunities identified for follow-up where warranted? | E43: Verify that lessons learned are captured and converted into useful project-specific and quality-system improvement opportunities. | O43: =IF('Review Register'!M3="","",'Review Register'!M3) | P43: =IF('Review Register'!D3="","",'Review Register'!D3)
A44: Project ID 03-R01 | B44: Project Record Accessibility / Organization | C44: 1.1 | D44: Are project records maintained in the Project Vault or another location permitted by the Project Vault SOP? | E44: Verify that material project records are stored in approved repositories with required traceability. | O44: =IF('Review Register'!M4="","",'Review Register'!M4) | P44: =IF('Review Register'!D4="","",'Review Register'!D4)
A45: Project ID 03-R01 | B45: Project Record Accessibility / Organization | C45: 1.2 | D45: Are the project’s primary source records readily locatable so the reviewer can understand what was sold, how the project was established for execution, and where supporting QSR evidence is maintained? | E45: Verify that primary source records can be readily located and used to establish the project basis and supporting evidence. | O45: =IF('Review Register'!M4="","",'Review Register'!M4) | P45: =IF('Review Register'!D4="","",'Review Register'!D4)
A46: Project ID 03-R01 | B46: Project Record Accessibility / Organization | C46: 1.3 | D46: Are project records organized, current, controlled, and sufficiently complete to support project execution, traceability, and reliable review? | E46: Verify the overall integrity, currency, control, and completeness of the project record for the lifecycle stage. | O46: =IF('Review Register'!M4="","",'Review Register'!M4) | P46: =IF('Review Register'!D4="","",'Review Register'!D4)
A47: Project ID 03-R01 | B47: Sales Handoff / Kickoff | C47: 2.1 | D47: Was Sales Handoff documented and effective in transferring the commercial, scope, schedule, budget, risk, client, and project-background information required by the PM and project team? | E47: Verify effective transfer of the information needed to move the project from sales/estimating into execution. | O47: =IF('Review Register'!M4="","",'Review Register'!M4) | P47: =IF('Review Register'!D4="","",'Review Register'!D4)
A48: Project ID 03-R01 | B48: Sales Handoff / Kickoff | C48: 2.2 | D48: Was the Internal Kickoff documented and effective in aligning the project team on scope, schedule, budget, responsibilities, quality expectations, risks, and the execution approach? | E48: Verify internal project-team alignment before or at the start of execution. | O48: =IF('Review Register'!M4="","",'Review Register'!M4) | P48: =IF('Review Register'!D4="","",'Review Register'!D4)
A49: Project ID 03-R01 | B49: Sales Handoff / Kickoff | C49: 2.3 | D49: Was the Client Kickoff documented and effective in aligning ETG and the client on scope, deliverables, schedule, responsibilities, communications, quality, risks, dependencies, approvals, and success expectations? | E49: Verify alignment between ETG and the client on how the project will be executed and governed. | O49: =IF('Review Register'!M4="","",'Review Register'!M4) | P49: =IF('Review Register'!D4="","",'Review Register'!D4)
A50: Project ID 03-R01 | B50: Project Planning / Workbook Usage | C50: 3.1 | D50: Were all applicable PMLC project-management planning areas considered and appropriately tailored to the project’s size, complexity, risk, contract, and execution needs? | E50: Verify that all applicable PMLC project-management planning areas were considered and appropriately tailored to the project. | O50: =IF('Review Register'!M4="","",'Review Register'!M4) | P50: =IF('Review Register'!D4="","",'Review Register'!D4)
A51: Project ID 03-R01 | B51: Project Planning / Workbook Usage | C51: 3.2 | D51: Were applicable Project Workbook components used and sufficiently populated to provide the required project-management records? | E51: Verify that applicable Project Workbook components supporting the Project Management Plan are used and sufficiently populated to serve as the intended project-management records. | O51: =IF('Review Register'!M4="","",'Review Register'!M4) | P51: =IF('Review Register'!D4="","",'Review Register'!D4)
A52: Project ID 03-R01 | B52: Project Planning / Workbook Usage | C52: 3.3 | D52: Were applicable project roles, responsibilities, deliverables, stakeholder needs, communications, resources, and schedule commitments clearly established and maintained? | E52: Verify that applicable roles and responsibilities, deliverables, stakeholder needs, communications, resources, and schedule commitments are established and maintained to support project execution. | O52: =IF('Review Register'!M4="","",'Review Register'!M4) | P52: =IF('Review Register'!D4="","",'Review Register'!D4)
A53: Project ID 03-R01 | B53: Risk Management | C53: 4.1 | D53: Were material project risks identified, assessed, and documented at appropriate points beginning with estimating and Sales Handoff? | E53: Verify that material project risks are identified and assessed at appropriate stages and that applicable pre-execution risks are carried forward into project planning. | O53: =IF('Review Register'!M4="","",'Review Register'!M4) | P53: =IF('Review Register'!D4="","",'Review Register'!D4)
A54: Project ID 03-R01 | B54: Risk Management | C54: 4.2 | D54: Was the Project Workbook Risk Registry used and maintained, or was an acceptable equivalent clearly identified and traceable through the Project Workbook or project records? | E54: Verify use of the standard Risk Registry or a clearly identified, traceable acceptable equivalent. | O54: =IF('Review Register'!M4="","",'Review Register'!M4) | P54: =IF('Review Register'!D4="","",'Review Register'!D4)
A55: Project ID 03-R01 | B55: Risk Management | C55: 4.3 | D55: Were risks reviewed throughout execution, with risk status, impacts, mitigation actions, owners, changes, and dispositions updated as warranted? | E55: Verify active management of identified risks throughout project execution. | O55: =IF('Review Register'!M4="","",'Review Register'!M4) | P55: =IF('Review Register'!D4="","",'Review Register'!D4)
A56: Project ID 03-R01 | B56: Change Management | C56: 5.1 | D56: Were potential or actual changes to scope, schedule, budget, requirements, design, or other approved project baselines identified and documented when they arose? | E56: Verify that material potential or actual changes to approved project baselines are recognized and documented when they arise. | O56: =IF('Review Register'!M4="","",'Review Register'!M4) | P56: =IF('Review Register'!D4="","",'Review Register'!D4)
A57: Project ID 03-R01 | B57: Change Management | C57: 5.2 | D57: Were changes evaluated, communicated, authorized, and approved before out-of-scope or at-risk work proceeded, except where the contract expressly permitted another approach? | E57: Verify that changes are evaluated and appropriately authorized before affected work proceeds. | O57: =IF('Review Register'!M4="","",'Review Register'!M4) | P57: =IF('Review Register'!D4="","",'Review Register'!D4)
A58: Project ID 03-R01 | B58: Change Management | C58: 5.3 | D58: Were approved changes fully incorporated into applicable project-management, financial, schedule, technical, contractual, and client records? | E58: Verify that approved changes are fully incorporated into the records and baselines they affect. | O58: =IF('Review Register'!M4="","",'Review Register'!M4) | P58: =IF('Review Register'!D4="","",'Review Register'!D4)
A59: Project ID 03-R01 | B59: Project Monitoring / Review Cadence | C59: 6.1 | D59: Were project reviews conducted at required or appropriate intervals, including applicable project checkpoints and recurring project reviews? | E59: Verify that project reviews and checkpoints occur at required or appropriate intervals. | O59: =IF('Review Register'!M4="","",'Review Register'!M4) | P59: =IF('Review Register'!D4="","",'Review Register'!D4)
A60: Project ID 03-R01 | B60: Project Monitoring / Review Cadence | C60: 6.2 | D60: Did project reviews address current scope, schedule, budget and forecast, risks, changes, deliverables, quality, resources, client needs, and other material project conditions as applicable? | E60: Verify that project reviews address the material conditions needed to understand and control project performance. | O60: =IF('Review Register'!M4="","",'Review Register'!M4) | P60: =IF('Review Register'!D4="","",'Review Register'!D4)
A61: Project ID 03-R01 | B61: Project Monitoring / Review Cadence | C61: 6.3 | D61: Were decisions, actions, owners, due dates, escalations, and follow-up resulting from project reviews documented and carried through? | E61: Verify that project-review decisions and actions are documented, assigned, escalated where needed, and followed through. | O61: =IF('Review Register'!M4="","",'Review Register'!M4) | P61: =IF('Review Register'!D4="","",'Review Register'!D4)
A62: Project ID 03-R01 | B62: Closeout / Lessons Learned | C62: 7.1 | D62: Were applicable technical, administrative, financial, contractual, and client closeout activities completed and documented? | E62: Verify completion and documentation of the applicable overall project closeout activities. | O62: =IF('Review Register'!M4="","",'Review Register'!M4) | P62: =IF('Review Register'!D4="","",'Review Register'!D4)
A63: Project ID 03-R01 | B63: Closeout / Lessons Learned | C63: 7.2 | D63: Were final deliverables, testing and acceptance records, turnover information, approved technical records, client signoffs, and other required closeout records completed and stored appropriately? | E63: Verify completion, approval, turnover, and proper storage of required final project records and deliverables. | O63: =IF('Review Register'!M4="","",'Review Register'!M4) | P63: =IF('Review Register'!D4="","",'Review Register'!D4)
A64: Project ID 03-R01 | B64: Closeout / Lessons Learned | C64: 7.3 | D64: Were lessons learned captured during the project and consolidated at closeout into useful recommendations, with project-specific and quality-system improvement opportunities identified for follow-up where warranted? | E64: Verify that lessons learned are captured and converted into useful project-specific and quality-system improvement opportunities. | O64: =IF('Review Register'!M4="","",'Review Register'!M4) | P64: =IF('Review Register'!D4="","",'Review Register'!D4)
A65: Project ID 04-R01 | B65: Project Record Accessibility / Organization | C65: 1.1 | D65: Are project records maintained in the Project Vault or another location permitted by the Project Vault SOP? | E65: Verify that material project records are stored in approved repositories with required traceability. | O65: =IF('Review Register'!M5="","",'Review Register'!M5) | P65: =IF('Review Register'!D5="","",'Review Register'!D5)
A66: Project ID 04-R01 | B66: Project Record Accessibility / Organization | C66: 1.2 | D66: Are the project’s primary source records readily locatable so the reviewer can understand what was sold, how the project was established for execution, and where supporting QSR evidence is maintained? | E66: Verify that primary source records can be readily located and used to establish the project basis and supporting evidence. | O66: =IF('Review Register'!M5="","",'Review Register'!M5) | P66: =IF('Review Register'!D5="","",'Review Register'!D5)
A67: Project ID 04-R01 | B67: Project Record Accessibility / Organization | C67: 1.3 | D67: Are project records organized, current, controlled, and sufficiently complete to support project execution, traceability, and reliable review? | E67: Verify the overall integrity, currency, control, and completeness of the project record for the lifecycle stage. | O67: =IF('Review Register'!M5="","",'Review Register'!M5) | P67: =IF('Review Register'!D5="","",'Review Register'!D5)
A68: Project ID 04-R01 | B68: Sales Handoff / Kickoff | C68: 2.1 | D68: Was Sales Handoff documented and effective in transferring the commercial, scope, schedule, budget, risk, client, and project-background information required by the PM and project team? | E68: Verify effective transfer of the information needed to move the project from sales/estimating into execution. | O68: =IF('Review Register'!M5="","",'Review Register'!M5) | P68: =IF('Review Register'!D5="","",'Review Register'!D5)
A69: Project ID 04-R01 | B69: Sales Handoff / Kickoff | C69: 2.2 | D69: Was the Internal Kickoff documented and effective in aligning the project team on scope, schedule, budget, responsibilities, quality expectations, risks, and the execution approach? | E69: Verify internal project-team alignment before or at the start of execution. | O69: =IF('Review Register'!M5="","",'Review Register'!M5) | P69: =IF('Review Register'!D5="","",'Review Register'!D5)
A70: Project ID 04-R01 | B70: Sales Handoff / Kickoff | C70: 2.3 | D70: Was the Client Kickoff documented and effective in aligning ETG and the client on scope, deliverables, schedule, responsibilities, communications, quality, risks, dependencies, approvals, and success expectations? | E70: Verify alignment between ETG and the client on how the project will be executed and governed. | O70: =IF('Review Register'!M5="","",'Review Register'!M5) | P70: =IF('Review Register'!D5="","",'Review Register'!D5)
A71: Project ID 04-R01 | B71: Project Planning / Workbook Usage | C71: 3.1 | D71: Were all applicable PMLC project-management planning areas considered and appropriately tailored to the project’s size, complexity, risk, contract, and execution needs? | E71: Verify that all applicable PMLC project-management planning areas were considered and appropriately tailored to the project. | O71: =IF('Review Register'!M5="","",'Review Register'!M5) | P71: =IF('Review Register'!D5="","",'Review Register'!D5)
A72: Project ID 04-R01 | B72: Project Planning / Workbook Usage | C72: 3.2 | D72: Were applicable Project Workbook components used and sufficiently populated to provide the required project-management records? | E72: Verify that applicable Project Workbook components supporting the Project Management Plan are used and sufficiently populated to serve as the intended project-management records. | O72: =IF('Review Register'!M5="","",'Review Register'!M5) | P72: =IF('Review Register'!D5="","",'Review Register'!D5)
A73: Project ID 04-R01 | B73: Project Planning / Workbook Usage | C73: 3.3 | D73: Were applicable project roles, responsibilities, deliverables, stakeholder needs, communications, resources, and schedule commitments clearly established and maintained? | E73: Verify that applicable roles and responsibilities, deliverables, stakeholder needs, communications, resources, and schedule commitments are established and maintained to support project execution. | O73: =IF('Review Register'!M5="","",'Review Register'!M5) | P73: =IF('Review Register'!D5="","",'Review Register'!D5)
A74: Project ID 04-R01 | B74: Risk Management | C74: 4.1 | D74: Were material project risks identified, assessed, and documented at appropriate points beginning with estimating and Sales Handoff? | E74: Verify that material project risks are identified and assessed at appropriate stages and that applicable pre-execution risks are carried forward into project planning. | O74: =IF('Review Register'!M5="","",'Review Register'!M5) | P74: =IF('Review Register'!D5="","",'Review Register'!D5)
A75: Project ID 04-R01 | B75: Risk Management | C75: 4.2 | D75: Was the Project Workbook Risk Registry used and maintained, or was an acceptable equivalent clearly identified and traceable through the Project Workbook or project records? | E75: Verify use of the standard Risk Registry or a clearly identified, traceable acceptable equivalent. | O75: =IF('Review Register'!M5="","",'Review Register'!M5) | P75: =IF('Review Register'!D5="","",'Review Register'!D5)
A76: Project ID 04-R01 | B76: Risk Management | C76: 4.3 | D76: Were risks reviewed throughout execution, with risk status, impacts, mitigation actions, owners, changes, and dispositions updated as warranted? | E76: Verify active management of identified risks throughout project execution. | O76: =IF('Review Register'!M5="","",'Review Register'!M5) | P76: =IF('Review Register'!D5="","",'Review Register'!D5)
A77: Project ID 04-R01 | B77: Change Management | C77: 5.1 | D77: Were potential or actual changes to scope, schedule, budget, requirements, design, or other approved project baselines identified and documented when they arose? | E77: Verify that material potential or actual changes to approved project baselines are recognized and documented when they arise. | O77: =IF('Review Register'!M5="","",'Review Register'!M5) | P77: =IF('Review Register'!D5="","",'Review Register'!D5)
A78: Project ID 04-R01 | B78: Change Management | C78: 5.2 | D78: Were changes evaluated, communicated, authorized, and approved before out-of-scope or at-risk work proceeded, except where the contract expressly permitted another approach? | E78: Verify that changes are evaluated and appropriately authorized before affected work proceeds. | O78: =IF('Review Register'!M5="","",'Review Register'!M5) | P78: =IF('Review Register'!D5="","",'Review Register'!D5)
A79: Project ID 04-R01 | B79: Change Management | C79: 5.3 | D79: Were approved changes fully incorporated into applicable project-management, financial, schedule, technical, contractual, and client records? | E79: Verify that approved changes are fully incorporated into the records and baselines they affect. | O79: =IF('Review Register'!M5="","",'Review Register'!M5) | P79: =IF('Review Register'!D5="","",'Review Register'!D5)
A80: Project ID 04-R01 | B80: Project Monitoring / Review Cadence | C80: 6.1 | D80: Were project reviews conducted at required or appropriate intervals, including applicable project checkpoints and recurring project reviews? | E80: Verify that project reviews and checkpoints occur at required or appropriate intervals. | O80: =IF('Review Register'!M5="","",'Review Register'!M5) | P80: =IF('Review Register'!D5="","",'Review Register'!D5)
A81: Project ID 04-R01 | B81: Project Monitoring / Review Cadence | C81: 6.2 | D81: Did project reviews address current scope, schedule, budget and forecast, risks, changes, deliverables, quality, resources, client needs, and other material project conditions as applicable? | E81: Verify that project reviews address the material conditions needed to understand and control project performance. | O81: =IF('Review Register'!M5="","",'Review Register'!M5) | P81: =IF('Review Register'!D5="","",'Review Register'!D5)
A82: Project ID 04-R01 | B82: Project Monitoring / Review Cadence | C82: 6.3 | D82: Were decisions, actions, owners, due dates, escalations, and follow-up resulting from project reviews documented and carried through? | E82: Verify that project-review decisions and actions are documented, assigned, escalated where needed, and followed through. | O82: =IF('Review Register'!M5="","",'Review Register'!M5) | P82: =IF('Review Register'!D5="","",'Review Register'!D5)
A83: Project ID 04-R01 | B83: Closeout / Lessons Learned | C83: 7.1 | D83: Were applicable technical, administrative, financial, contractual, and client closeout activities completed and documented? | E83: Verify completion and documentation of the applicable overall project closeout activities. | O83: =IF('Review Register'!M5="","",'Review Register'!M5) | P83: =IF('Review Register'!D5="","",'Review Register'!D5)
A84: Project ID 04-R01 | B84: Closeout / Lessons Learned | C84: 7.2 | D84: Were final deliverables, testing and acceptance records, turnover information, approved technical records, client signoffs, and other required closeout records completed and stored appropriately? | E84: Verify completion, approval, turnover, and proper storage of required final project records and deliverables. | O84: =IF('Review Register'!M5="","",'Review Register'!M5) | P84: =IF('Review Register'!D5="","",'Review Register'!D5)
A85: Project ID 04-R01 | B85: Closeout / Lessons Learned | C85: 7.3 | D85: Were lessons learned captured during the project and consolidated at closeout into useful recommendations, with project-specific and quality-system improvement opportunities identified for follow-up where warranted? | E85: Verify that lessons learned are captured and converted into useful project-specific and quality-system improvement opportunities. | O85: =IF('Review Register'!M5="","",'Review Register'!M5) | P85: =IF('Review Register'!D5="","",'Review Register'!D5)
A86: Project ID 05-R01 | B86: Project Record Accessibility / Organization | C86: 1.1 | D86: Are project records maintained in the Project Vault or another location permitted by the Project Vault SOP? | E86: Verify that material project records are stored in approved repositories with required traceability. | O86: =IF('Review Register'!M6="","",'Review Register'!M6) | P86: =IF('Review Register'!D6="","",'Review Register'!D6)
A87: Project ID 05-R01 | B87: Project Record Accessibility / Organization | C87: 1.2 | D87: Are the project’s primary source records readily locatable so the reviewer can understand what was sold, how the project was established for execution, and where supporting QSR evidence is maintained? | E87: Verify that primary source records can be readily located and used to establish the project basis and supporting evidence. | O87: =IF('Review Register'!M6="","",'Review Register'!M6) | P87: =IF('Review Register'!D6="","",'Review Register'!D6)
A88: Project ID 05-R01 | B88: Project Record Accessibility / Organization | C88: 1.3 | D88: Are project records organized, current, controlled, and sufficiently complete to support project execution, traceability, and reliable review? | E88: Verify the overall integrity, currency, control, and completeness of the project record for the lifecycle stage. | O88: =IF('Review Register'!M6="","",'Review Register'!M6) | P88: =IF('Review Register'!D6="","",'Review Register'!D6)
A89: Project ID 05-R01 | B89: Sales Handoff / Kickoff | C89: 2.1 | D89: Was Sales Handoff documented and effective in transferring the commercial, scope, schedule, budget, risk, client, and project-background information required by the PM and project team? | E89: Verify effective transfer of the information needed to move the project from sales/estimating into execution. | O89: =IF('Review Register'!M6="","",'Review Register'!M6) | P89: =IF('Review Register'!D6="","",'Review Register'!D6)
A90: Project ID 05-R01 | B90: Sales Handoff / Kickoff | C90: 2.2 | D90: Was the Internal Kickoff documented and effective in aligning the project team on scope, schedule, budget, responsibilities, quality expectations, risks, and the execution approach? | E90: Verify internal project-team alignment before or at the start of execution. | O90: =IF('Review Register'!M6="","",'Review Register'!M6) | P90: =IF('Review Register'!D6="","",'Review Register'!D6)
A91: Project ID 05-R01 | B91: Sales Handoff / Kickoff | C91: 2.3 | D91: Was the Client Kickoff documented and effective in aligning ETG and the client on scope, deliverables, schedule, responsibilities, communications, quality, risks, dependencies, approvals, and success expectations? | E91: Verify alignment between ETG and the client on how the project will be executed and governed. | O91: =IF('Review Register'!M6="","",'Review Register'!M6) | P91: =IF('Review Register'!D6="","",'Review Register'!D6)
A92: Project ID 05-R01 | B92: Project Planning / Workbook Usage | C92: 3.1 | D92: Were all applicable PMLC project-management planning areas considered and appropriately tailored to the project’s size, complexity, risk, contract, and execution needs? | E92: Verify that all applicable PMLC project-management planning areas were considered and appropriately tailored to the project. | O92: =IF('Review Register'!M6="","",'Review Register'!M6) | P92: =IF('Review Register'!D6="","",'Review Register'!D6)
A93: Project ID 05-R01 | B93: Project Planning / Workbook Usage | C93: 3.2 | D93: Were applicable Project Workbook components used and sufficiently populated to provide the required project-management records? | E93: Verify that applicable Project Workbook components supporting the Project Management Plan are used and sufficiently populated to serve as the intended project-management records. | O93: =IF('Review Register'!M6="","",'Review Register'!M6) | P93: =IF('Review Register'!D6="","",'Review Register'!D6)
A94: Project ID 05-R01 | B94: Project Planning / Workbook Usage | C94: 3.3 | D94: Were applicable project roles, responsibilities, deliverables, stakeholder needs, communications, resources, and schedule commitments clearly established and maintained? | E94: Verify that applicable roles and responsibilities, deliverables, stakeholder needs, communications, resources, and schedule commitments are established and maintained to support project execution. | O94: =IF('Review Register'!M6="","",'Review Register'!M6) | P94: =IF('Review Register'!D6="","",'Review Register'!D6)
A95: Project ID 05-R01 | B95: Risk Management | C95: 4.1 | D95: Were material project risks identified, assessed, and documented at appropriate points beginning with estimating and Sales Handoff? | E95: Verify that material project risks are identified and assessed at appropriate stages and that applicable pre-execution risks are carried forward into project planning. | O95: =IF('Review Register'!M6="","",'Review Register'!M6) | P95: =IF('Review Register'!D6="","",'Review Register'!D6)
A96: Project ID 05-R01 | B96: Risk Management | C96: 4.2 | D96: Was the Project Workbook Risk Registry used and maintained, or was an acceptable equivalent clearly identified and traceable through the Project Workbook or project records? | E96: Verify use of the standard Risk Registry or a clearly identified, traceable acceptable equivalent. | O96: =IF('Review Register'!M6="","",'Review Register'!M6) | P96: =IF('Review Register'!D6="","",'Review Register'!D6)
A97: Project ID 05-R01 | B97: Risk Management | C97: 4.3 | D97: Were risks reviewed throughout execution, with risk status, impacts, mitigation actions, owners, changes, and dispositions updated as warranted? | E97: Verify active management of identified risks throughout project execution. | O97: =IF('Review Register'!M6="","",'Review Register'!M6) | P97: =IF('Review Register'!D6="","",'Review Register'!D6)
A98: Project ID 05-R01 | B98: Change Management | C98: 5.1 | D98: Were potential or actual changes to scope, schedule, budget, requirements, design, or other approved project baselines identified and documented when they arose? | E98: Verify that material potential or actual changes to approved project baselines are recognized and documented when they arise. | O98: =IF('Review Register'!M6="","",'Review Register'!M6) | P98: =IF('Review Register'!D6="","",'Review Register'!D6)
A99: Project ID 05-R01 | B99: Change Management | C99: 5.2 | D99: Were changes evaluated, communicated, authorized, and approved before out-of-scope or at-risk work proceeded, except where the contract expressly permitted another approach? | E99: Verify that changes are evaluated and appropriately authorized before affected work proceeds. | O99: =IF('Review Register'!M6="","",'Review Register'!M6) | P99: =IF('Review Register'!D6="","",'Review Register'!D6)
A100: Project ID 05-R01 | B100: Change Management | C100: 5.3 | D100: Were approved changes fully incorporated into applicable project-management, financial, schedule, technical, contractual, and client records? | E100: Verify that approved changes are fully incorporated into the records and baselines they affect. | O100: =IF('Review Register'!M6="","",'Review Register'!M6) | P100: =IF('Review Register'!D6="","",'Review Register'!D6)
...

Sheet Scoring Guide
A1: Review Area | B1: Question ID | C1: Controlled Question | D1: 3 — Meets Expectation | E1: 2 — Partially Meets Expectation | F1: 1 — Does Not Meet Expectation | G1: Typical Evidence | H1: Evaluation Boundary
A2: Project Record Accessibility / Organization | B2: 1.1 | C2: Are project records maintained in the Project Vault or another location permitted by the Project Vault SOP? | D2: Material records are in Project Vault or permitted alternate locations with required traceability. | E2: Most records comply, but some material records or required links are inconsistently maintained. | F2: Material records are outside approved locations or cannot be traced to an approved repository. | G2: Project Vault project folder and applicable standard subfolders; records applicable to the project; links to approved alternate storage locations, including large files, virtual machines, or client-hosted deliverables. | H2: Evaluates whether records applicable to the project are maintained in an approved repository. Applicability depends on the project’s scope, execution approach, and activities performed. The existence of a standard Project Vault folder or template does not, by itself, mean the corresponding record is required. Does not evaluate general file organization or the substantive adequacy of individual records.
A3: Project Record Accessibility / Organization | B3: 1.2 | C3: Are the project’s primary source records readily locatable so the reviewer can understand what was sold, how the project was established for execution, and where supporting QSR evidence is maintained? | D3: Primary source records are readily found without material searching or PM assistance. | E3: Records are ultimately found, but some require PM assistance or are stored unexpectedly. | F3: Material source records cannot be reliably located or verified after clarification. | G3: Contract/authorization; proposal; estimate/WBS; Workbook; Notebook; schedule; approved links. | H3: Scores findability—not the quality of each underlying process record.
A4: Project Record Accessibility / Organization | B4: 1.3 | C4: Are project records organized, current, controlled, and sufficiently complete to support project execution, traceability, and reliable review? | D4: Records are substantially current, controlled, and complete for the project stage. | E4: Records are usable but contain material gaps, outdated information, unclear versions, or incomplete approvals. | F4: Records are materially disorganized, outdated, uncontrolled, or incomplete. | G4: Representative files; current logs/registers; approvals; revisions; links; final records. | H4: Scores overall record integrity—not isolated process-artifact failures.
A5: Sales Handoff / Kickoff | B5: 2.1 | C5: Was Sales Handoff documented and effective in transferring the commercial, scope, schedule, budget, risk, client, and project-background information required by the PM and project team? | D5: Handoff is documented and materially transfers the information needed for successful technical and commercial execution. | E5: Handoff occurred and transferred meaningful information, but material elements, documentation, or communication are incomplete. | F5: Handoff is absent, cannot be reliably evidenced, or fails to transfer material information needed for execution. | G5: Sales Handover agenda and meeting minutes documenting discussion or transfer of applicable project information, including scope and deliverables, schedule, budget/WBS, risks and opportunities, client expectations/contacts, contractual or commercial considerations, and relevant project background; referenced or attached supporting records where identified in the handoff documentation; PM clarification where the documented handoff is unclear. | H5: Evaluates whether applicable information was actually transferred from Sales to Operations, based primarily on the documented Sales Handover and targeted PM clarification where needed. The existence of underlying sales or project records alone does not demonstrate that the information was communicated during the handoff.
A6: Sales Handoff / Kickoff | B6: 2.2 | C6: Was the Internal Kickoff documented and effective in aligning the project team on scope, schedule, budget, responsibilities, quality expectations, risks, and the execution approach? | D6: Internal Kickoff is documented and materially aligns the project team on the required execution topics. | E6: Kickoff occurred and provides meaningful alignment, but material topics, participants, minutes, or follow-up are incomplete. | F6: Kickoff is absent, cannot be reliably evidenced, or does not materially align the project team on execution expectations. | G6: Internal Kickoff agenda/minutes; RACI; proposal; schedule; WBS/budget; Risk Registry; quality-role assignments. | H6: Scores internal team alignment; do not duplicate Sales Handoff or Client Kickoff unless separately deficient.
A7: Sales Handoff / Kickoff | B7: 2.3 | C7: Was the Client Kickoff documented and effective in aligning ETG and the client on scope, deliverables, schedule, responsibilities, communications, quality, risks, dependencies, approvals, and success expectations? | D7: Client Kickoff is documented and materially establishes shared understanding of the applicable project expectations. | E7: Kickoff occurred and establishes meaningful alignment, but material topics, documentation, or follow-up are incomplete. | F7: Kickoff is absent, cannot be reliably evidenced, or fails to establish material ETG/client alignment. | G7: Client Kickoff agenda/minutes; proposal; deliverables; preliminary schedule; roles; communication expectations; risks/dependencies; approval expectations. | H7: Scores initial ETG/client alignment; do not duplicate Internal Kickoff or ongoing project communications/reviews unless separately deficient.
A8: Project Planning / Workbook Usage | B8: 3.1 | C8: Were all applicable PMLC project-management planning areas considered and appropriately tailored to the project’s size, complexity, risk, contract, and execution needs? | D8: All applicable PMLC project-management planning areas were considered, and the planning approach was appropriately tailored to the project’s size, complexity, risk, contract, and execution needs. Material N/A or tailored treatment is reasonably supported. | E8: Most applicable planning areas were considered, but one or more material areas were not clearly addressed, applicability or tailoring is inadequately supported, or the planning approach contains material gaps. | F8: Required project-management planning was largely not performed or cannot be reliably evidenced, or material planning areas were not considered such that an appropriate project-management approach was not established. | G8: Begin with the PM Plan Checklist and confirm that each applicable PMLC planning area was considered and that an appropriate planning approach was established for the project. Review supporting records only to the extent necessary to verify the existence and reasonable adequacy of the initial plan: Scope Management — Deliverables Log, Change Log, applicable scope/requirements records; Schedule Management — project schedule; Budget Management — WBS/budget and Intacct; Quality Management — Project Checkpoint and applicable quality planning; Resource Management — SRM/resource planning; Communications Management — Communication Plan; Risk Management — Risk Registry; Procurement Management — applicable procurement planning/records; Stakeholder Management — Stakeholder Registry. Detailed record maintenance and substantive execution of these controls are evaluated under subsequent questions where applicable. | H8: Evaluates whether the applicable PMLC management areas were considered and appropriately tailored—not the detailed completeness, currency, or ongoing effectiveness of each supporting control. Deficiencies covered by a more specific QSR question are scored under that question rather than duplicated here.
A9: Project Planning / Workbook Usage | B9: 3.2 | C9: Were applicable Project Workbook components used and sufficiently populated to provide the required project-management records? | D9: Applicable Project Workbook components are used and populated sufficiently to serve as the required project-management records for the project. | E9: The Project Workbook is meaningfully used, but one or more material applicable components are incomplete, inconsistently populated, or require clarification to function as reliable project-management records | F9: Applicable Project Workbook components are largely unused, absent, or insufficiently populated to provide reliable project-management records. | G9: Applicable Project Workbook worksheets supporting the Project Management Plan, including the PM Plan Checklist, Communication Plan, Stakeholder Registry, Deliverables Log, Change Log, and Risk Registry. Each applicable worksheet should contain sufficient project-specific information to demonstrate that the applicable management area has been addressed and to function as the intended project-management record. Blank worksheets, template/example content, placeholders, or entries that do not provide enough information to understand what is being managed do not constitute sufficient population. Sufficient population is based on the information reasonably required for the worksheet to perform its intended role on the project and does not require entries for conditions or events that have not occurred. | H9: Evaluates use and population of applicable Project Workbook components—not the substantive effectiveness of the management processes represented by those components. Risk, change, review, and other controls having dedicated QSR questions are evaluated under those questions.
A10: Project Planning / Workbook Usage | B10: 3.3 | C10: Were applicable project roles, responsibilities, deliverables, stakeholder needs, communications, resources, and schedule commitments clearly established and maintained? | D10: Applicable roles, deliverables, stakeholders, communications, resources, and schedule commitments are clearly established and maintained. | E10: Applicable roles and responsibilities, deliverables, stakeholder needs, communications, resources, and schedule commitments were clearly established and maintained sufficiently to support project execution. | F10: Most applicable elements were established, but one or more material elements became incomplete, unclear, outdated, or inconsistently maintained during execution. | G10: Evidence that applicable execution-management elements were established and maintained as the project progressed, including: RACI or equivalent evidence of current project roles and responsibilities; Deliverables Log or equivalent evidence identifying applicable deliverables, ownership, status, and commitments; Stakeholder Registry showing applicable stakeholders and relevant engagement information; Communication Plan showing the project’s communication needs, participants, methods, and cadence; current project schedule reflecting applicable activities, milestones, dependencies, and commitments; SRM/resource planning reflecting the resources needed for execution; and kickoff, project-review, or other project records that substantiate material updates or changes to these elements during execution. Evidence should be evaluated based on the project’s scope, stage, complexity, and execution needs. | H10: Evaluates establishment and ongoing maintenance of roles/responsibilities, deliverables, stakeholder needs, communications, resources, and schedule commitments. Does not score general Workbook completeness or controls addressed by dedicated risk, change, project-review, or other QSR questions.
A11: Risk Management | B11: 4.1 | C11: Were material project risks identified, assessed, and documented at appropriate points beginning with estimating and Sales Handoff? | D11: Material risks were identified and assessed at appropriate stages beginning with estimating/proposal development, and applicable risks were documented and carried forward through Sales Handoff into project planning/execution. Evidence demonstrates a reasonably complete and traceable progression of material risks appropriate to the project. | E11: Meaningful risk identification and assessment occurred, but one or more material aspects are incomplete or inconsistent—for example, some material risks were identified late, assessment was incomplete, transfer from estimating/Sales Handoff is only partially evidenced, or applicable risks were not consistently carried forward into project planning. | F11: Material risk identification and assessment were largely absent, materially inadequate, or cannot be reliably evidenced after reasonable record review and PM clarification; or significant known risks were not transferred into project planning/execution such that the required risk-identification process was not meaningfully performed. | G11: Evidence of risk identification and assessment at the applicable project stages, including: estimating/proposal risk assessment or risk register showing risks identified during development of the estimate and proposal; proposal or supporting sales records documenting material risks, assumptions, or uncertainties where applicable; Sales Handover agenda/minutes documenting transfer and discussion of identified risks and opportunities; and the initial Project Workbook Risk Registry showing risks carried forward from Sales and risks identified during project planning. PM clarification may be used to understand when and how risks were identified or transferred where the records are unclear. | H11: Evaluates whether material risks were identified and assessed at appropriate stages and whether applicable pre-execution risks were carried forward into project planning. The Risk Registry may be reviewed as evidence of identification and transfer, but the risk-recording mechanism and traceability are evaluated under 4.2, and ongoing review, mitigation, ownership, status, and disposition are evaluated under 4.3.
A12: Risk Management | B12: 4.2 | C12: Was the Project Workbook Risk Registry used and maintained, or was an acceptable equivalent clearly identified and traceable through the Project Workbook or project records? | D12: The Project Workbook Risk Registry is used and maintained, or an equivalent is clearly identified, controlled, traceable, and functionally equivalent. | E12: A risk record exists and is usable, but maintenance, traceability, equivalence, or identification of the alternate method is materially incomplete. | F12: The expected risk record is absent, an alternate method is not clearly identified/equivalent, or material risks cannot be reliably traced. | G12: Project Workbook Risk Registry; clearly identified alternate risk register; Workbook/reference link; project records showing the controlled equivalent. | H12: Scores the risk-recording mechanism and traceability; do not duplicate initial risk identification or ongoing risk management unless separately deficient.
... A22: Closeout / Lessons Learned | B22: 7.3 | C22: Were lessons learned captured during the project and consolidated at closeout into useful recommendations, with project-specific and quality-system improvement opportunities identified for follow-up where warranted? | D22: Lessons are captured during execution and consolidated at closeout into clear, useful insights/actions for future project and quality-system improvement. | E22: Meaningful lessons are documented, but capture, consolidation, context, recommendations, or follow-up identification is materially incomplete. | F22: Lessons learned are largely absent, cannot be reliably evidenced, or are too incomplete to provide useful improvement learning. | G22: Lessons Learned Log; lessons learned meeting minutes; action items/recommendations; reusable asset/case-study identification; closeout records. | H22: Scores lessons learned and improvement capture; do not duplicate general closeout completion or final deliverable records unless separately deficient.

Sheet Source Matrix
A1: Review Area | B1: Question ID | C1: Source Document | D1: Section | E1: Page | F1: Requirement / Relevance | G1: Source File
A2: Project Record Accessibility / Organization | B2: 1.1 | C2: OPS-SOP-Project-Vault | D2: §1–2 | E2: 3 | F2: Establishes standard project storage architecture and approved storage requirements. | G2: OPS-SOP-Project-Vault.docx
A3: Project Record Accessibility / Organization | B3: 1.1 | C3: OPS-SOP-Project-Vault | D3: §5.4–5.8 | E3: 4–5 | F3: Defines folder architecture and permitted large-file and virtual-machine storage. | G3: OPS-SOP-Project-Vault.docx
A4: Project Record Accessibility / Organization | B4: 1.1 | C4: OPS-SOP-Project-Vault | D4: §5.14.1–5.14.4 | E4: 7–8 | F4: Defines treatment of client-hosted deliverables and required tracking. | G4: OPS-SOP-Project-Vault.docx
A5: Project Record Accessibility / Organization | B5: 1.1 | C5: OPS-SP-System Development Life Cycle | D5: §5.1.9 | E5: 5 | F5: Requires project-related files to follow the Project Vault SOP. | G5: OPS-SP-System-Development-Life-Cycle.pdf
A6: Project Record Accessibility / Organization | B6: 1.2 | C6: QSR Program Discussion Summary | D6: §§7–9 | E6: 5–7 | F6: Establishes file-first review, PM clarification, and evidence-location treatment. | G6: QSR Program Discussion Summary 260707.docx
A7: Project Record Accessibility / Organization | B7: 1.2 | C7: Project Notebook | D7: Sales Handover Agenda | E7: 16 | F7: Identifies primary source records expected during handoff preparation. | G7: Project-Notebook.pdf
A8: Project Record Accessibility / Organization | B8: 1.2 | C8: Project Workbook | D8: Information worksheet | E8: N/A | F8: Identifies integrated project-management records and expected storage location. | G8: Project Workbook_rev3_[ProjectId] (1).xlsx
A9: Project Record Accessibility / Organization | B9: 1.3 | C9: OPS-SOP-Project-Vault | D9: §5.3–5.6 | E9: 4 | F9: Defines organization, folder control, and project-file maintenance requirements. | G9: OPS-SOP-Project-Vault.docx
A10: Project Record Accessibility / Organization | B10: 1.3 | C10: OPS-SOP-Project-Vault | D10: §5.14.1–5.14.4 | E10: 7–8 | F10: Requires approved, named, version-controlled final records and centralized tracking. | G10: OPS-SOP-Project-Vault.docx
A11: Project Record Accessibility / Organization | B11: 1.3 | C11: OPS-SP-System Development Life Cycle | D11: §5.1.2–5.1.9 | E11: 5 | F11: Requires documented approvals, controlled records, client signoffs, and Vault storage. | G11: OPS-SP-System-Development-Life-Cycle.pdf
A12: Sales Handoff / Kickoff | B12: 2.1 | C12: OPS-SP-Project Management Life Cycle | D12: §6.1.2 | E12: 6 | F12: Defines Sales to Operations Handover intent, required agenda/minutes, and transfer of scope, objectives, Client expectations, risks/opportunities, and project history. | G12: OPS-SP-Project-Management-Life-Cycle.pdf
... A67: Closeout / Lessons Learned | B67: 7.3 | C67: Project Notebook | D67: Lessons Learned Guidance and Lessons Learned Agenda Template | E67: Instructions Pages 10–13; Internal Pages 27–28 | F67: Provides the standard approach for reviewing the Lessons Learned Log, consolidating insights/recommendations, and identifying follow-up actions. | G67: Project-Notebook.pdf

Sheet Actions
A1: Action ID | B1: Review ID | C1: Question ID | D1: Action Type | E1: Action / Improvement | F1: Owner | G1: Due Date | H1: Status | I1: Closure Evidence | J1: Closed Date | K1: Notes

Sheet KPI Summary
A1: KPI | B1: Definition | C1: Value | E1: Root Cause Category | F1: Frequency | G1: Distribution
A2: Overall Conformance Rate | B2: Percentage of applicable Initial Review questions scored 3 — Meets Expectation. | C2: {=IFERROR( SUMPRODUCT( --(LEFT(ReviewEntryTable[Result],1)="3"), --(_xlfn.XLOOKUP(ReviewEntryTable[Review ID],ReviewRegisterTable[Review ID],ReviewRegisterTable[Review Type],"")="Initial Review") ) / SUMPRODUCT( --(((LEFT(ReviewEntryTable[Result],1)="3")+ (LEFT(ReviewEntryTable[Result],1)="2")+ (LEFT(ReviewEntryTable[Result],1)="1"))>0), --(_xlfn.XLOOKUP(ReviewEntryTable[Review ID],ReviewRegisterTable[Review ID],ReviewRegisterTable[Review Type],"")="Initial Review") ), 0)} -> 0 | E2: Standard Not Followed | F2: {=SUMPRODUCT( --(ReviewEntryTable[Primary Root Cause]=E2), --((LEFT(ReviewEntryTable[Result],1)="1")+(LEFT(ReviewEntryTable[Result],1)="2")>0), --(_xlfn.XLOOKUP( ReviewEntryTable[Review ID], ReviewRegisterTable[Review ID], ReviewRegisterTable[Review Type], "" )="Initial Review") )} -> 0 | G2: =IFERROR(F2/SUM($F$2:$F$7),0) -> 0
A3: System-Related Gap Rate | B3: Percentage of gaps (ratings 1 or 2) primarily related to quality-system design or enablement. | C3: {=IFERROR( SUMPRODUCT( --((LEFT(ReviewEntryTable[Result],1)="1")+(LEFT(ReviewEntryTable[Result],1)="2")>0), --(_xlfn.XLOOKUP(ReviewEntryTable[Review ID],ReviewRegisterTable[Review ID],ReviewRegisterTable[Review Type],"")="Initial Review"), --ISNUMBER(MATCH( ReviewEntryTable[Primary Root Cause], {"Standard Unclear","Tool / Template Friction","Training Gap","Workload / Capacity Constraint","Governance / Enforcement Gap"}, 0)) ) / SUMPRODUCT( --((LEFT(ReviewEntryTable[Result],1)="1")+(LEFT(ReviewEntryTable[Result],1)="2")>0), --(_xlfn.XLOOKUP(ReviewEntryTable[Review ID],ReviewRegisterTable[Review ID],ReviewRegisterTable[Review Type],"")="Initial Review"), --ISNUMBER(MATCH( ReviewEntryTable[Primary Root Cause], {"Standard Not Followed","Standard Unclear","Tool / Template Friction","Training Gap","Workload / Capacity Constraint","Governance / Enforcement Gap"}, 0)) ), 0)} -> 0 | E3: Standard Unclear | F3: {=SUMPRODUCT( --(ReviewEntryTable[Primary Root Cause]=E3), --((LEFT(ReviewEntryTable[Result],1)="1")+(LEFT(ReviewEntryTable[Result],1)="2")>0), --(_xlfn.XLOOKUP( ReviewEntryTable[Review ID], ReviewRegisterTable[Review ID], ReviewRegisterTable[Review Type], "" )="Initial Review") )} -> 0 | G3: =IFERROR(F3/SUM($F$2:$F$7),0) -> 0
A4: Evidence Control Gap Rate | B4: Percentage of applicable Initial Review questions with incomplete, missing, inaccessible, misfiled, or not-maintained evidence. Excludes N/A and UTD records. | C4: {=IFERROR( SUMPRODUCT( --ISNUMBER(MATCH( ReviewEntryTable[Evidence Status], {"Incomplete Evidence","Missing Evidence","Inaccessible Evidence","Misfiled Evidence","Not Maintained as Expected"}, 0)), --(((LEFT(ReviewEntryTable[Result],1)="3")+ (LEFT(ReviewEntryTable[Result],1)="2")+ (LEFT(ReviewEntryTable[Result],1)="1"))>0), --(_xlfn.XLOOKUP(ReviewEntryTable[Review ID],ReviewRegisterTable[Review ID],ReviewRegisterTable[Review Type],"")="Initial Review") ) / SUMPRODUCT( --(((LEFT(ReviewEntryTable[Result],1)="3")+ (LEFT(ReviewEntryTable[Result],1)="2")+ (LEFT(ReviewEntryTable[Result],1)="1"))>0), --(_xlfn.XLOOKUP(ReviewEntryTable[Review ID],ReviewRegisterTable[Review ID],ReviewRegisterTable[Review Type],"")="Initial Review") ), 0)} -> 0 | E4: Tool / Template Friction | F4: {=SUMPRODUCT( --(ReviewEntryTable[Primary Root Cause]=E4), --((LEFT(ReviewEntryTable[Result],1)="1")+(LEFT(ReviewEntryTable[Result],1)="2")>0), --(_xlfn.XLOOKUP( ReviewEntryTable[Review ID], ReviewRegisterTable[Review ID], ReviewRegisterTable[Review Type], "" )="Initial Review") )} -> 0 | G4: =IFERROR(F4/SUM($F$2:$F$7),0) -> 0
A5: Alternate Evidence Rate | B5: Percentage of applicable Initial Review questions supported by acceptable alternate evidence. Excludes N/A and UTD records. | C5: {=IFERROR( SUMPRODUCT( --(ReviewEntryTable[Evidence Status]="Acceptable Alternate Evidence"), --(((LEFT(ReviewEntryTable[Result],1)="3")+ (LEFT(ReviewEntryTable[Result],1)="2")+ (LEFT(ReviewEntryTable[Result],1)="1"))>0), --(_xlfn.XLOOKUP(ReviewEntryTable[Review ID],ReviewRegisterTable[Review ID],ReviewRegisterTable[Review Type],"")="Initial Review") ) / SUMPRODUCT( --(((LEFT(ReviewEntryTable[Result],1)="3")+ (LEFT(ReviewEntryTable[Result],1)="2")+ (LEFT(ReviewEntryTable[Result],1)="1"))>0), --(_xlfn.XLOOKUP(ReviewEntryTable[Review ID],ReviewRegisterTable[Review ID],ReviewRegisterTable[Review Type],"")="Initial Review") ), 0)} -> 0 | E5: Training Gap | F5: {=SUMPRODUCT( --(ReviewEntryTable[Primary Root Cause]=E5), --((LEFT(ReviewEntryTable[Result],1)="1")+(LEFT(ReviewEntryTable[Result],1)="2")>0), --(_xlfn.XLOOKUP( ReviewEntryTable[Review ID], ReviewRegisterTable[Review ID], ReviewRegisterTable[Review Type], "" )="Initial Review") )} -> 0 | G5: =IFERROR(F5/SUM($F$2:$F$7),0) -> 0
A6: Completion Rate for Initial Reviews | B6: Percentage of planned Initial review instances marked Completed. | C6: =IFERROR( COUNTIFS( ReviewRegisterTable[Review Type],"Initial Review", ReviewRegisterTable[Review Status],"Completed" )/ COUNTIF( ReviewRegisterTable[Review Type],"Initial Review" ),0) -> 0 | E6: Workload / Capacity Constraint | F6: {=SUMPRODUCT( --(ReviewEntryTable[Primary Root Cause]=E6), --((LEFT(ReviewEntryTable[Result],1)="1")+(LEFT(ReviewEntryTable[Result],1)="2")>0), --(_xlfn.XLOOKUP( ReviewEntryTable[Review ID], ReviewRegisterTable[Review ID], ReviewRegisterTable[Review Type], "" )="Initial Review") )} -> 0 | G6: =IFERROR(F6/SUM($F$2:$F$7),0) -> 0
A7: Average Initial Review Time (Hours) | B7: Average reviewer time for completed Initial Reviews with recorded review time. | C7: =IFERROR( AVERAGEIFS( ReviewRegisterTable[Review Time (Hours)], ReviewRegisterTable[Review Type],"Initial Review", ReviewRegisterTable[Review Status],"Completed", ReviewRegisterTable[Review Time (Hours)],">0" ),0) -> 0 | E7: Governance / Enforcement Gap | F7: {=SUMPRODUCT( --(ReviewEntryTable[Primary Root Cause]=E7), --((LEFT(ReviewEntryTable[Result],1)="1")+(LEFT(ReviewEntryTable[Result],1)="2")>0), --(_xlfn.XLOOKUP( ReviewEntryTable[Review ID], ReviewRegisterTable[Review ID], ReviewRegisterTable[Review Type], "" )="Initial Review") )} -> 0 | G7: =IFERROR(F7/SUM($F$2:$F$7),0) -> 0
A9: Supporting Statistic | B9: Definition | C9: Value | E9: Review Area | F9: Score | G9: Conformance Rate
A10: Total Review Instances | B10: Total number of review instances established in the Review Register. | C10: =COUNTIF(ReviewRegisterTable[Review ID],"<>") -> 5 | E10: Project Record Accessibility / Organization | F10: {=IFERROR( ( SUMPRODUCT( --(ReviewEntryTable[Review Area]=E10), --(_xlfn.XLOOKUP(ReviewEntryTable[Review ID],ReviewRegisterTable[Review ID],ReviewRegisterTable[Review Type],"")="Initial Review"), --(LEFT(ReviewEntryTable[Result],1)="3") )*3 + SUMPRODUCT( --(ReviewEntryTable[Review Area]=E10), --(_xlfn.XLOOKUP(ReviewEntryTable[Review ID],ReviewRegisterTable[Review ID],ReviewRegisterTable[Review Type],"")="Initial Review"), --(LEFT(ReviewEntryTable[Result],1)="2") )*2 + SUMPRODUCT( --(ReviewEntryTable[Review Area]=E10), --(_xlfn.XLOOKUP(ReviewEntryTable[Review ID],ReviewRegisterTable[Review ID],ReviewRegisterTable[Review Type],"")="Initial Review"), --(LEFT(ReviewEntryTable[Result],1)="1") ) ) / SUMPRODUCT( --(ReviewEntryTable[Review Area]=E10), --(_xlfn.XLOOKUP(ReviewEntryTable[Review ID],ReviewRegisterTable[Review ID],ReviewRegisterTable[Review Type],"")="Initial Review"), --(((LEFT(ReviewEntryTable[Result],1)="3")+ (LEFT(ReviewEntryTable[Result],1)="2")+ (LEFT(ReviewEntryTable[Result],1)="1"))>0) ), 0)} -> 0 | G10: {=IFERROR( SUMPRODUCT( --(ReviewEntryTable[Review Area]=E10), --(LEFT(ReviewEntryTable[Result],1)="3"), --(_xlfn.XLOOKUP(ReviewEntryTable[Review ID],ReviewRegisterTable[Review ID],ReviewRegisterTable[Review Type],"")="Initial Review") ) / SUMPRODUCT( --(ReviewEntryTable[Review Area]=E10), --(((LEFT(ReviewEntryTable[Result],1)="3")+ (LEFT(ReviewEntryTable[Result],1)="2")+ (LEFT(ReviewEntryTable[Result],1)="1"))>0), --(_xlfn.XLOOKUP(ReviewEntryTable[Review ID],ReviewRegisterTable[Review ID],ReviewRegisterTable[Review Type],"")="Initial Review") ), 0)} -> 0
A11: Completed Reviews | B11: Number of review instances marked Completed. | C11: =COUNTIF(ReviewRegisterTable[Review Status],"Completed") -> 0 | E11: Sales Handoff / Kickoff | F11: {=IFERROR( ( SUMPRODUCT( --(ReviewEntryTable[Review Area]=E11), --(_xlfn.XLOOKUP(ReviewEntryTable[Review ID],ReviewRegisterTable[Review ID],ReviewRegisterTable[Review Type],"")="Initial Review"), --(LEFT(ReviewEntryTable[Result],1)="3") )*3 + SUMPRODUCT( --(ReviewEntryTable[Review Area]=E11), --(_xlfn.XLOOKUP(ReviewEntryTable[Review ID],ReviewRegisterTable[Review ID],ReviewRegisterTable[Review Type],"")="Initial Review"), --(LEFT(ReviewEntryTable[Result],1)="2") )*2 + SUMPRODUCT( --(ReviewEntryTable[Review Area]=E11), --(_xlfn.XLOOKUP(ReviewEntryTable[Review ID],ReviewRegisterTable[Review ID],ReviewRegisterTable[Review Type],"")="Initial Review"), --(LEFT(ReviewEntryTable[Result],1)="1") ) ) / SUMPRODUCT( --(ReviewEntryTable[Review Area]=E11), --(_xlfn.XLOOKUP(ReviewEntryTable[Review ID],ReviewRegisterTable[Review ID],ReviewRegisterTable[Review Type],"")="Initial Review"), --(((LEFT(ReviewEntryTable[Result],1)="3")+ (LEFT(ReviewEntryTable[Result],1)="2")+ (LEFT(ReviewEntryTable[Result],1)="1"))>0) ), 0)} -> 0 | G11: {=IFERROR( SUMPRODUCT( --(ReviewEntryTable[Review Area]=E11), --(LEFT(ReviewEntryTable[Result],1)="3"), --(_xlfn.XLOOKUP(ReviewEntryTable[Review ID],ReviewRegisterTable[Review ID],ReviewRegisterTable[Review Type],"")="Initial Review") ) / SUMPRODUCT( --(ReviewEntryTable[Review Area]=E11), --(((LEFT(ReviewEntryTable[Result],1)="3")+ (LEFT(ReviewEntryTable[Result],1)="2")+ (LEFT(ReviewEntryTable[Result],1)="1"))>0), --(_xlfn.XLOOKUP(ReviewEntryTable[Review ID],ReviewRegisterTable[Review ID],ReviewRegisterTable[Review Type],"")="Initial Review") ), 0)} -> 0
A12: Applicable Question Results | B12: Total questions scored 3, 2, or 1; excludes N/A and UTD. | C12: =(COUNTIF(ReviewEntryTable[Result],"3*")+COUNTIF(ReviewEntryTable[Result],"2*")+COUNTIF(ReviewEntryTable[Result],"1*")) -> 0 | E12: Project Planning / Workbook Usage | F12: {=IFERROR( ( SUMPRODUCT( --(ReviewEntryTable[Review Area]=E12), --(_xlfn.XLOOKUP(ReviewEntryTable[Review ID],ReviewRegisterTable[Review ID],ReviewRegisterTable[Review Type],"")="Initial Review"), --(LEFT(ReviewEntryTable[Result],1)="3") )*3 + SUMPRODUCT( --(ReviewEntryTable[Review Area]=E12), --(_xlfn.XLOOKUP(ReviewEntryTable[Review ID],ReviewRegisterTable[Review ID],ReviewRegisterTable[Review Type],"")="Initial Review"), --(LEFT(ReviewEntryTable[Result],1)="2") )*2 + SUMPRODUCT( --(ReviewEntryTable[Review Area]=E12), --(_xlfn.XLOOKUP(ReviewEntryTable[Review ID],ReviewRegisterTable[Review ID],ReviewRegisterTable[Review Type],"")="Initial Review"), --(LEFT(ReviewEntryTable[Result],1)="1") ) ) / SUMPRODUCT( --(ReviewEntryTable[Review Area]=E12), --(_xlfn.XLOOKUP(ReviewEntryTable[Review ID],ReviewRegisterTable[Review ID],ReviewRegisterTable[Review Type],"")="Initial Review"), --(((LEFT(ReviewEntryTable[Result],1)="3")+ (LEFT(ReviewEntryTable[Result],1)="2")+ (LEFT(ReviewEntryTable[Result],1)="1"))>0) ), 0)} -> 0 | G12: {=IFERROR( SUMPRODUCT( --(ReviewEntryTable[Review Area]=E12), --(LEFT(ReviewEntryTable[Result],1)="3"), --(_xlfn.XLOOKUP(ReviewEntryTable[Review ID],ReviewRegisterTable[Review ID],ReviewRegisterTable[Review Type],"")="Initial Review") ) / SUMPRODUCT( --(ReviewEntryTable[Review Area]=E12), --(((LEFT(ReviewEntryTable[Result],1)="3")+ (LEFT(ReviewEntryTable[Result],1)="2")+ (LEFT(ReviewEntryTable[Result],1)="1"))>0), --(_xlfn.XLOOKUP(ReviewEntryTable[Review ID],ReviewRegisterTable[Review ID],ReviewRegisterTable[Review Type],"")="Initial Review") ), 0)} -> 0
A13: Gap Rate | B13: Percentage of applicable Initial Review questions scored 1 or 2. | C13: {=IFERROR( SUMPRODUCT( --(((LEFT(ReviewEntryTable[Result],1)="1")+ (LEFT(ReviewEntryTable[Result],1)="2"))>0), --(_xlfn.XLOOKUP(ReviewEntryTable[Review ID],ReviewRegisterTable[Review ID],ReviewRegisterTable[Review Type],"")="Initial Review") ) / SUMPRODUCT( --(((LEFT(ReviewEntryTable[Result],1)="3")+ (LEFT(ReviewEntryTable[Result],1)="2")+ (LEFT(ReviewEntryTable[Result],1)="1"))>0), --(_xlfn.XLOOKUP(ReviewEntryTable[Review ID],ReviewRegisterTable[Review ID],ReviewRegisterTable[Review Type],"")="Initial Review") ), 0)} -> 0 | E13: Risk Management | F13: {=IFERROR( ( SUMPRODUCT( --(ReviewEntryTable[Review Area]=E13), --(_xlfn.XLOOKUP(ReviewEntryTable[Review ID],ReviewRegisterTable[Review ID],ReviewRegisterTable[Review Type],"")="Initial Review"), --(LEFT(ReviewEntryTable[Result],1)="3") )*3 + SUMPRODUCT( --(ReviewEntryTable[Review Area]=E13), --(_xlfn.XLOOKUP(ReviewEntryTable[Review ID],ReviewRegisterTable[Review ID],ReviewRegisterTable[Review Type],"")="Initial Review"), --(LEFT(ReviewEntryTable[Result],1)="2") )*2 + SUMPRODUCT( --(ReviewEntryTable[Review Area]=E13), --(_xlfn.XLOOKUP(ReviewEntryTable[Review ID],ReviewRegisterTable[Review ID],ReviewRegisterTable[Review Type],"")="Initial Review"), --(LEFT(ReviewEntryTable[Result],1)="1") ) ) / SUMPRODUCT( --(ReviewEntryTable[Review Area]=E13), --(_xlfn.XLOOKUP(ReviewEntryTable[Review ID],ReviewRegisterTable[Review ID],ReviewRegisterTable[Review Type],"")="Initial Review"), --(((LEFT(ReviewEntryTable[Result],1)="3")+ (LEFT(ReviewEntryTable[Result],1)="2")+ (LEFT(ReviewEntryTable[Result],1)="1"))>0) ), 0)} -> 0 | G13: {=IFERROR( SUMPRODUCT( --(ReviewEntryTable[Review Area]=E13), --(LEFT(ReviewEntryTable[Result],1)="3"), --(_xlfn.XLOOKUP(ReviewEntryTable[Review ID],ReviewRegisterTable[Review ID],ReviewRegisterTable[Review Type],"")="Initial Review") ) / SUMPRODUCT( --(ReviewEntryTable[Review Area]=E13), --(((LEFT(ReviewEntryTable[Result],1)="3")+ (LEFT(ReviewEntryTable[Result],1)="2")+ (LEFT(ReviewEntryTable[Result],1)="1"))>0), --(_xlfn.XLOOKUP(ReviewEntryTable[Review ID],ReviewRegisterTable[Review ID],ReviewRegisterTable[Review Type],"")="Initial Review") ), 0)} -> 0
E14: Change Management | F14: {=IFERROR( ( SUMPRODUCT( --(ReviewEntryTable[Review Area]=E14), --(_xlfn.XLOOKUP(ReviewEntryTable[Review ID],ReviewRegisterTable[Review ID],ReviewRegisterTable[Review Type],"")="Initial Review"), --(LEFT(ReviewEntryTable[Result],1)="3") )*3 + SUMPRODUCT( --(ReviewEntryTable[Review Area]=E14), --(_xlfn.XLOOKUP(ReviewEntryTable[Review ID],ReviewRegisterTable[Review ID],ReviewRegisterTable[Review Type],"")="Initial Review"), --(LEFT(ReviewEntryTable[Result],1)="2") )*2 + SUMPRODUCT( --(ReviewEntryTable[Review Area]=E14), --(_xlfn.XLOOKUP(ReviewEntryTable[Review ID],ReviewRegisterTable[Review ID],ReviewRegisterTable[Review Type],"")="Initial Review"), --(LEFT(ReviewEntryTable[Result],1)="1") ) ) / SUMPRODUCT( --(ReviewEntryTable[Review Area]=E14), --(_xlfn.XLOOKUP(ReviewEntryTable[Review ID],ReviewRegisterTable[Review ID],ReviewRegisterTable[Review Type],"")="Initial Review"), --(((LEFT(ReviewEntryTable[Result],1)="3")+ (LEFT(ReviewEntryTable[Result],1)="2")+ (LEFT(ReviewEntryTable[Result],1)="1"))>0) ), 0)} -> 0 | G14: {=IFERROR( SUMPRODUCT( --(ReviewEntryTable[Review Area]=E14), --(LEFT(ReviewEntryTable[Result],1)="3"), --(_xlfn.XLOOKUP(ReviewEntryTable[Review ID],ReviewRegisterTable[Review ID],ReviewRegisterTable[Review Type],"")="Initial Review") ) / SUMPRODUCT( --(ReviewEntryTable[Review Area]=E14), --(((LEFT(ReviewEntryTable[Result],1)="3")+ (LEFT(ReviewEntryTable[Result],1)="2")+ (LEFT(ReviewEntryTable[Result],1)="1"))>0), --(_xlfn.XLOOKUP(ReviewEntryTable[Review ID],ReviewRegisterTable[Review ID],ReviewRegisterTable[Review Type],"")="Initial Review") ), 0)} -> 0
E15: Project Monitoring / Review Cadence | F15: {=IFERROR( ( SUMPRODUCT( --(ReviewEntryTable[Review Area]=E15), --(_xlfn.XLOOKUP(ReviewEntryTable[Review ID],ReviewRegisterTable[Review ID],ReviewRegisterTable[Review Type],"")="Initial Review"), --(LEFT(ReviewEntryTable[Result],1)="3") )*3 + SUMPRODUCT( --(ReviewEntryTable[Review Area]=E15), --(_xlfn.XLOOKUP(ReviewEntryTable[Review ID],ReviewRegisterTable[Review ID],ReviewRegisterTable[Review Type],"")="Initial Review"), --(LEFT(ReviewEntryTable[Result],1)="2") )*2 + SUMPRODUCT( --(ReviewEntryTable[Review Area]=E15), --(_xlfn.XLOOKUP(ReviewEntryTable[Review ID],ReviewRegisterTable[Review ID],ReviewRegisterTable[Review Type],"")="Initial Review"), --(LEFT(ReviewEntryTable[Result],1)="1") ) ) / SUMPRODUCT( --(ReviewEntryTable[Review Area]=E15), --(_xlfn.XLOOKUP(ReviewEntryTable[Review ID],ReviewRegisterTable[Review ID],ReviewRegisterTable[Review Type],"")="Initial Review"), --(((LEFT(ReviewEntryTable[Result],1)="3")+ (LEFT(ReviewEntryTable[Result],1)="2")+ (LEFT(ReviewEntryTable[Result],1)="1"))>0) ), 0)} -> 0 | G15: {=IFERROR( SUMPRODUCT( --(ReviewEntryTable[Review Area]=E15), --(LEFT(ReviewEntryTable[Result],1)="3"), --(_xlfn.XLOOKUP(ReviewEntryTable[Review ID],ReviewRegisterTable[Review ID],ReviewRegisterTable[Review Type],"")="Initial Review") ) / SUMPRODUCT( --(ReviewEntryTable[Review Area]=E15), --(((LEFT(ReviewEntryTable[Result],1)="3")+ (LEFT(ReviewEntryTable[Result],1)="2")+ (LEFT(ReviewEntryTable[Result],1)="1"))>0), --(_xlfn.XLOOKUP(ReviewEntryTable[Review ID],ReviewRegisterTable[Review ID],ReviewRegisterTable[Review Type],"")="Initial Review") ), 0)} -> 0
E16: Closeout / Lessons Learned | F16: {=IFERROR( ( SUMPRODUCT( --(ReviewEntryTable[Review Area]=E16), --(_xlfn.XLOOKUP(ReviewEntryTable[Review ID],ReviewRegisterTable[Review ID],ReviewRegisterTable[Review Type],"")="Initial Review"), --(LEFT(ReviewEntryTable[Result],1)="3") )*3 + SUMPRODUCT( --(ReviewEntryTable[Review Area]=E16), --(_xlfn.XLOOKUP(ReviewEntryTable[Review ID],ReviewRegisterTable[Review ID],ReviewRegisterTable[Review Type],"")="Initial Review"), --(LEFT(ReviewEntryTable[Result],1)="2") )*2 + SUMPRODUCT( --(ReviewEntryTable[Review Area]=E16), --(_xlfn.XLOOKUP(ReviewEntryTable[Review ID],ReviewRegisterTable[Review ID],ReviewRegisterTable[Review Type],"")="Initial Review"), --(LEFT(ReviewEntryTable[Result],1)="1") ) ) / SUMPRODUCT( --(ReviewEntryTable[Review Area]=E16), --(_xlfn.XLOOKUP(ReviewEntryTable[Review ID],ReviewRegisterTable[Review ID],ReviewRegisterTable[Review Type],"")="Initial Review"), --(((LEFT(ReviewEntryTable[Result],1)="3")+ (LEFT(ReviewEntryTable[Result],1)="2")+ (LEFT(ReviewEntryTable[Result],1)="1"))>0) ), 0)} -> 0 | G16: {=IFERROR( SUMPRODUCT( --(ReviewEntryTable[Review Area]=E16), --(LEFT(ReviewEntryTable[Result],1)="3"), --(_xlfn.XLOOKUP(ReviewEntryTable[Review ID],ReviewRegisterTable[Review ID],ReviewRegisterTable[Review Type],"")="Initial Review") ) / SUMPRODUCT( --(ReviewEntryTable[Review Area]=E16), --(((LEFT(ReviewEntryTable[Result],1)="3")+ (LEFT(ReviewEntryTable[Result],1)="2")+ (LEFT(ReviewEntryTable[Result],1)="1"))>0), --(_xlfn.XLOOKUP(ReviewEntryTable[Review ID],ReviewRegisterTable[Review ID],ReviewRegisterTable[Review Type],"")="Initial Review") ), 0)} -> 0

Sheet Lists
A1: BU | B1: Project Status | C1: Review Type | D1: Review Status | E1: Review Area | F1: Result | G1: Evidence Status | H1: Yes / No | I1: Primary Root Cause | J1: Quality-System-Related? | K1: Action Type | L1: Action Status
A2: Central | B2: Active | C2: Initial Review | D2: Not Started | E2: Project Record Accessibility / Organization | F2: 3 - Meets Expectation | G2: Expected Evidence Found | H2: Yes | I2: Individual Adherence Gap | J2: Yes | K2: Project Correction | L2: Open
A3: East | B3: Completed | C3: Follow-Up Review | D3: In Progress | E3: Sales Handoff / Kickoff | F3: 2 - Partially Meets Expectation | G3: Acceptable Alternate Evidence | H3: No | I3: Standard Unclear | J3: No | K3: Standard / Process | L3: In Progress
A4: GL | D4: Completed | E4: Project Planning / Workbook Usage | F4: 1 - Does Not Meet Expectation | G4: Incomplete Evidence | I4: Tool / Template Friction | J4: Further Evaluation Needed | K4: Tool / Template | L4: Closed
A5: MCT | E5: Risk Management | F5: N/A - Not Applicable | G5: Missing Evidence | I5: Training Gap | K5: Training / Communication | L5: Deferred
A6: West | E6: Change Management | F6: UTD - Unable to Determine | G6: Inaccessible Evidence | I6: Workload / Capacity Constraint | K6: Governance
E7: Project Monitoring / Review Cadence | G7: Misfiled Evidence | I7: Governance / Enforcement Gap | K7: Further Evaluation
E8: Closeout / Lessons Learned | G8: Not Maintained as Expected
G9: Not Applicable
